Workbook

Sheet LEDGER
A3: Cost Code | B3: Date | C3: Invoice # | D3: Payee | E3: Description | F3: Amount | G3: Amount Paid | H3: Amount Due | I3: Funding Source
A4: 0.0001 | D4: Disbursement #00 | F4: 593250 | G4: 593250 | H4: =F4-G4 | I4: VENTANAS I
A5: 0.0002 | D5: Disbursement #00 | F5: 7507599.7 | G5: 7507599.7 | H5: =F5-G5 | I5: VENTANAS I
A6: 0.0002 | D6: Disbursement #00 | F6: 1875000 | G6: 1875000 | H6: =F6-G6 | I6: VENTANAS I
A7: 0.3.1 | D7: Disbursement #00 | F7: 7950 | G7: 0 | H7: =F7-G7
A8: 0.4 | D8: Disbursement #00 | F8: 11250 | G8: 0 | H8: =F8-G8
A9: 0.6.2 | D9: Disbursement #00 | F9: 4800 | G9: 0 | H9: =F9-G9
A10: 0.6.3 | D10: Disbursement #00 | F10: 2400 | G10: 0 | H10: =F10-G10
A11: 0.7 | D11: Disbursement #00 | F11: 42375 | G11: 0 | H11: =F11-G11
A12: 0.8 | D12: Disbursement #00 | F12: 20000 | G12: 0 | H12: =F12-G12
A13: 0.9 | D13: Disbursement #00 | F13: 6000 | G13: 0 | H13: =F13-G13
A14: 0.9 | D14: Disbursement #00 | F14: 6480 | G14: 0 | H14: =F14-G14
A15: 2.1.1 | D15: Disbursement #00 | F15: 14500 | G15: 0 | H15: =F15-G15
A16: 3.1 | D16: Disbursement #00 | F16: 8236.005 | G16: 0 | H16: =F16-G16
A17: 3.3 | D17: Disbursement #00 | F17: 3779.624 | G17: 0 | H17: =F17-G17
A18: 3.4 | D18: Disbursement #00 | F18: 7342.175 | G18: 0 | H18: =F18-G18
... A25: 0.1 | D25: Disbursement #00 | F25: 450000 | G25: 450000 | H25: =F25-G25
A26: 3.2 | D26: Disbursement #01 - 06/05/2024 | E26: Topography Lidar | F26: 25000 | G26: 25000 | H26: =F26-G26
A27: 3.2 | D27: Disbursement #01 - 06/05/2024 | E27: Topography vat tax Pending | F27: 3250 | G27: 3250 | H27: =F27-G27
A28: 0.0001 | D28: Disbursement #01 - 06/05/2024 | E28: Soil analysis | F28: 10170 | G28: 10170 | H28: =F28-G28
A29: 0.0001 | D29: Disbursement #01 - 06/05/2024 | E29: Boundary Analysis and Marking | F29: 5085 | G29: 5085 | H29: =F29-G29
A30: 0.0001 | D30: Disbursement #01 - 06/05/2024 | E30: Water testing | F30: 1915.35 | G30: 1915.35 | H30: =F30-G30
A31: 0.0001 | D31: Disbursement #01 - 06/05/2024 | E31: Environmental Feasibility Report | F31: 8737.16 | G31: 8737.16 | H31: =F31-G31
A32: 0.0001 | D32: Disbursement #01 - 06/05/2024 | E32: Tree Trimming $880+Vat per day | F32: 4972 | G32: 4972 | H32: =F32-G32
A33: 0.3.1 | D33: Disbursement #01 - 06/05/2024 | E33: Constitution of 13 Corps | F33: 0 | G33: 0 | H33: =F33-G33
A34: 0.3.1 | D34: Disbursement #01 - 06/05/2024 | E34: 13 Certifications for Muni Application | F34: 983.1 | G34: 983.1 | H34: =F34-G34
A35: 0.3.1 | D35: Disbursement #01 - 06/05/2024 | E35: Constitution of 2 Corps | F35: 2034 | G35: 2034 | H35: =F35-G35
A36: 0.2 | D36: Disbursement #01 - 06/05/2024 | E36: 2 Certifications for Muni Application | F36: 151.25 | G36: 151.25 | H36: =F36-G36
A37: 0.0001 | D37: Disbursement #01 - 06/05/2024 | E37: Legal Fees (local Attorney plus Municipal and Environmental fees) | F37: 25000 | G37: 25000 | H37: =F37-G37
... A126: 6.3 | D126: Disbursement #09 - 04/10/2025 | E126: Work with topographer | F126: 141.25 | G126: 141.25 | H126: =F126-G126
A127: 0.7 | D127: Disbursement #10 - 05/01/2025 | E127: Development Director Abril 2025 | F127: 14125 | G127: 14125 | H127: =F127-G127 | I127: 14125
A128: 0.4 | D128: Disbursement #10 - 05/01/2025 | E128: Admin Fee Budget + Financial Controller 25% Salary Abril 2025 | F128: 3750 | G128: 3750 | H128: =F128-G128 | I128: 6150
A129: 0.6.1 | D129: Disbursement #10 - 05/01/2025 | E129: Farm Manager + Worker April 2025 | F129: 1600 | G129: 1600 | H129: =F129-G129 | I129: 6150
A130: 0.6.1 | D130: Disbursement #10 - 05/01/2025 | E130: CCSS (Social Security) April 2025 | F130: 800 | G130: 800 | H130: =F130-G130 | I130: 6150
A131: 6.3 | D131: Disbursement #10 - 05/01/2025 | E131: Internal Road (Cinco Ventanas) Materials | F131: 4000 | G131: 4000 | H131: =F131-G131
A132: 0.5 | D132: Disbursement #10 - 05/01/2025 | E132: Owners expenses pay back to CWL | F132: 14851.54 | G132: 14851.54 | H132: =F132-G132
A133: 0.911 | D133: Disbursement #10 - 05/01/2025 | E133: Construction Works in Piñuela – Gates | F133: 1400 | G133: 1400 | H133: =F133-G133
A134: 3.1 | D134: Disbursement #10 - 05/01/2025 | E134: Forest stratification technical analysis. | F134: 3390 | G134: 3390 | H134: =F134-G134
A135: 0.7 | D135: Disbursement #11 - 06/01/2025 | E135: Development Director MAY 2025 | F135: 14125 | G135: 14125 | H135: =F135-G135 | I135: 14125
A136: 0.4 | D136: Disbursement #11 - 06/01/2025 | E136: Admin Fee Budget + Financial Controller 25% Salary MAY 2025 | F136: 3750 | G136: 3750 | H136: =F136-G136 | I136: 6150
A137: 0.6.1 | D137: Disbursement #11 - 06/01/2025 | E137: Farm Manager + Worker MAY 2025 | F137: 1600 | G137: 1600 | H137: =F137-G137 | I137: 6150
A138: 0.6.1 | D138: Disbursement #11 - 06/01/2025 | E138: CCSS (Social Security) MAY 2025 | F138: 800 | G138: 800 | H138: =F138-G138 | I138: 6150
A139: 3.1 | D139: Disbursement #11 - 06/01/2025 | E139: YEDIER GUSTAVO GAMBOA CERDAS | F139: 380 | G139: 380 | H139: =F139-G139 | I139: 380
A140: 3.1 | D140: Disbursement #11 - 06/01/2025 | E140: YEDIER GUSTAVO GAMBOA CERDAS | F140: 1130 | G140: 1130 | H140: =F140-G140 | I140: 1130
A141: 0.6.4 | D141: Disbursement #11 - 06/01/2025 | E141: ALTA BATALLA | F141: 30 | G141: 30 | H141: =F141-G141 | I141: 5002
A142: 0.6.4 | D142: Disbursement #11 - 06/01/2025 | E142: ALTA BATALLA | F142: 1017 | G142: 1017 | H142: =F142-G142 | I142: 5002
A143: 0.6.4 | D143: Disbursement #11 - 06/01/2025 | E143: ALTA BATALLA | F143: 3955 | G143: 3955 | H143: =F143-G143 | I143: 5002
A144: 0.5 | D144: Disbursement #11 - 06/01/2025 | E144: NACASCOLO AIR (SJO TO VENTANAS) | F144: 4620 | G144: 4620 | H144: =F144-G144 | I144: 7467.61
A145: 0.5 | D145: Disbursement #11 - 06/01/2025 | E145: NACASCOLO AIR (QUEPOS TO SJO) | F145: 2847.6 | G145: 2847.6 | H145: =F145-G145 | I145: 7467.61
A146: 0.5 | D146: Disbursement #11 - 06/01/2025 | E146: OXIGEN JUNGLE VILLAS | F146: 3101.85 | G146: 3101.85 | H146: =F146-G146 | I146: 3101.85
A147: 5.8 | D147: Disbursement #11 - 06/01/2025 | E147: Topography Services | F147: 15000 | G147: 0 | H147: =F147-G147
A148: 5.8 | D148: Disbursement #11 - 06/01/2025 | E148: Legal: Concessions and Muncipality Meetings | F148: 7500 | G148: 0 | H148: =F148-G148
A149: 0.7 | D149: Disbursement #12 - 07/01/2025 | E149: Development Director JUNE 2025 | F149: 14125 | G149: 14125 | H149: =F149-G149 | I149: 14125
A150: 0.4 | D150: Disbursement #12 - 07/01/2025 | E150: Admin Fee Budget + Financial Controller 25% Salary JUNE 2025 | F150: 3750 | G150: 3750 | H150: =F150-G150 | I150: 6150
A151: 0.4 | D151: Disbursement #12 - 07/01/2025 | E151: Farm Manager + Worker JUNE 2025 | F151: 1600 | G151: 1600 | H151: =F151-G151 | I151: 6150
A152: 0.4 | D152: Disbursement #12 - 07/01/2025 | E152: CCSS (Social Security) JUNE 2025 | F152: 800 | G152: 800 | H152: =F152-G152 | I152: 6150
A153: 1.4 | D153: Disbursement #12 - 07/01/2025 | E153: Water System 70% Downpayment of 155 000.00 ($109500) PAID $46500 | F153: 109500 | G153: 109500 | H153: =F153-G153
A154: 0.5 | D154: Disbursement #12 - 07/01/2025 | E154: Invoice from Oxigen for Meals | F154: 137.39 | G154: 137.39 | H154: =F154-G154 | I154: 137.39
A155: 3.1 | D155: Disbursement #12 - 07/01/2025 | E155: Treeming for view Ventanas with Blake and Karol | F155: 1130 | G155: 1130 | H155: =F155-G155 | I155: 1130
A156: 3.1 | D156: Disbursement #12 - 07/01/2025 | E156: Pura Selva clearing the area for the gaviones | F156: 380 | G156: 380 | H156: =F156-G156 | I156: 380
A157: 3.1 | D157: Disbursement #12 - 07/01/2025 | E157: Shey Coordinated | F157: 2576 | G157: 2576 | H157: =F157-G157 | I157: 2576
A158: 1.4 | D158: Disbursement #12 - 07/01/2025 | E158: PIPELINE CROSSING CONSTRUCTION PROJECT – PLAYA VENTANAS $14880+IVA | F158: 16814.4 | G158: 16814.4 | H158: =F158-G158
A159: 0.7 | D159: Disbursement #13 - 08/01/2025 | E159: Development Director August 2025 | F159: 14125 | G159: 14125 | H159: =F159-G159 | I159: 14125
A160: 0.4 | D160: Disbursement #13 - 08/01/2025 | E160: Admin Fee Budget + Financial Controller 25% Salary AUGUST 2025 | F160: 3750 | G160: 3750 | H160: =F160-G160 | I160: 6150
A161: 0.6.1 | D161: Disbursement #13 - 08/01/2025 | E161: Farm Manager + Worker AUGUST 2025 | F161: 1600 | G161: 1600 | H161: =F161-G161 | I161: 6150
A162: 0.6.1 | D162: Disbursement #13 - 08/01/2025 | E162: CCSS (Social Security) AUGUST 2025 | F162: 800 | G162: 800 | H162: =F162-G162 | I162: 6150
A163: 6.3 | D163: Disbursement #13 - 08/01/2025 | E163: Entrance Pura Selva -5 VENTANAS (Total $5694.00 Minus $5400 Previous wired) | F163: 294 | G163: 0 | H163: =F163-G163
A164: 3.1 | D164: Disbursement #13 - 08/01/2025 | E164: Environmental Forestry Study-ALTA BATALLA (Permitting process) | F164: 4350.5 | G164: 4350.5 | H164: =F164-G164 | I164: 4350.5
A165: 0.7 | D165: Disbursement #14 - 09/01/2025 | E165: Development Director SEPTEMBER 2025 | F165: 14125 | G165: 14125 | H165: =F165-G165 | I165: 14125
A166: 0.4 | D166: Disbursement #14 - 09/01/2025 | E166: Admin Fee Budget + Financial Controller 25% Salary SEPTEMBER 2025 | F166: 3750 | G166: 3750 | H166: =F166-G166 | I166: 6150
A167: 0.6.1 | D167: Disbursement #14 - 09/01/2025 | E167: Farm Manager + Worker SEPTEMBER 2025 | F167: 1600 | G167: 1600 | H167: =F167-G167 | I167: 6150
A168: 0.6.1 | D168: Disbursement #14 - 09/01/2025 | E168: CCSS (Social Security) SEPTEMBER 2025 | F168: 800 | G168: 800 | H168: =F168-G168 | I168: 6150
A169: 0.6.2 | D169: Disbursement #14 - 09/01/2025 | E169: Alex Payment- Care Taker Ventanas | F169: 1120 | G169: 1120 | H169: =F169-G169
A170: 1.4 | D170: Disbursement #14 - 09/01/2025 | E170: Final payment + extra drilling under highway + water meters | F170: 32500 | G170: 32500 | H170: =F170-G170
A171: 0.7 | D171: Disbursement #15 - 10/01/2025 | E171: Development Director OCTOBER 2025 | F171: 14125 | G171: 14125 | H171: =F171-G171 | I171: 14125
A172: 0.4 | D172: Disbursement #15 - 10/01/2025 | E172: Admin Fee Budget + Financial Controller 25% Salary OCTOBER 2025 | F172: 3750 | G172: 3750 | H172: =F172-G172 | I172: 6150
A173: 0.6.1 | D173: Disbursement #15 - 10/01/2025 | E173: Farm Manager + Worker OCTOBER 2025 | F173: 1600 | G173: 1600 | H173: =F173-G173 | I173: 6150
A174: 0.6.1 | D174: Disbursement #15 - 10/01/2025 | E174: CCSS (Social Security) OCTOBER 2025 | F174: 800 | G174: 800 | H174: =F174-G174 | I174: 6150
A175: 0.6.2 | D175: Disbursement #15 - 10/01/2025 | E175: Alex Payment- Care Taker Ventanas | F175: 1000 | G175: 0 | H175: =F175-G175
A176: 3.1 | D176: Disbursement #15 - 10/01/2025 | E176: DEHC for road alignment $2385.00 plus IVA | F176: 2695.05 | G176: 2695.05 | H176: =F176-G176 | I176: 3359.5
A177: 3.1 | D177: Disbursement #15 - 10/01/2025 | E177: CASTRO & DE LA TORRE: Soil Studies IVA | F177: 312.24599 | G177: 0 | H177: =F177-G177
A178: 3.1 | D178: Disbursement #15 - 10/01/2025 | E178: FOREST INSPECTION $1585.00 plus IVA | F178: 1791.05 | G178: 0 | H178: =F178-G178
A179: 0.7 | D179: Disbursement #16 - 11/01/2025 | E179: Development Director NOVEMBER 2025 | F179: 14125 | G179: 14125 | H179: =F179-G179 | I179: 14125
A180: 0.4 | D180: Disbursement #16 - 11/01/2025 | E180: Admin Fee Budget + Financial Controller 25% Salary NOVEMBER 2025 | F180: 3750 | G180: 3750 | H180: =F180-G180 | I180: 3750
A181: 0.6.1 | D181: Disbursement #16 - 11/01/2025 | E181: Farm Manager + Worker NOVEMBER 2025 | F181: 1600 | G181: 1600 | H181: =F181-G181 | I181: 1600
A182: 0.6.1 | D182: Disbursement #16 - 11/01/2025 | E182: CCSS (Social Security) NOVEMBER 2025 | F182: 800 | G182: 800 | H182: =F182-G182 | I182: 800
A183: 0.6.2 | D183: Disbursement #16 - 11/01/2025 | E183: Alex Payment- Care Taker Ventanas | F183: 1824.705 | G183: 1824.705 | H183: =F183-G183 | I183: 1824.705
A184: 3.1 | D184: Disbursement #16 - 11/01/2025 | E184: DEHC for road alignment Pending Previous Request $4255 +IVA | F184: 4808.15 | G184: 4808.15 | H184: =F184-G184 | I184: 3943.7
A185: 3.1 | D185: Disbursement #16 - 11/01/2025 | E185: CASTRO & DE LA TORRE: Soil Studies + IVA | F185: 312.24599 | G185: 0 | H185: =F185-G185
A186: 3.1 | D186: Disbursement #16 - 11/01/2025 | E186: SEED: Developer Milestone accomplishment for water certification for access and system acceptance: $25,000 + VAT | F186: 28250 | G186: 28250 | H186: =F186-G186 | I186: 28249.999999999996
A187: 3.1 | D187: Disbursement #16 - 11/01/2025 | E187: Ojachal Garderns. Permit Engineer, Forestry Engineer, Land Surveyor DEHC Stay C Stay Aug 11, 2025 | F187: 813.6 | G187: 813.6 | H187: =F187-G187
A188: 3.1 | D188: Disbursement #16 - 11/01/2025 | E188: Ojachal Garderns. Permit Engineer, Forestry Engineer, Land Surveyor DEHC Stay Stay Aug 26, 2025 | F188: 310.64 | G188: 310.64 | H188: =F188-G188
A189: 3.1 | D189: Disbursement #16 - 11/01/2025 | E189: Ojachal Garderns. Permit Engineer, Forestry Engineer, Land Surveyor DEHC Stay Stay Oct 14-15, 2025 | F189: 542.4 | G189: 542.4 | H189: =F189-G189
A190: 3.1 | D190: Disbursement #16 - 11/01/2025 | E190: ALTA BATALLA: Annual Fee Ventanas Administration Trust | F190: 3616 | G190: 3616 | H190: =F190-G190
A191: 0.6.4 | D191: Disbursement #16 - 11/01/2025 | E191: Ferreteria Palmares: Materiales | F191: 1003.9 | G191: 0 | H191: =F191-G191
A192: 1.4 | D192: Disbursement #16 - 11/01/2025 | E192: Water Meters ASADA | F192: 555 | G192: 0 | H192: =F192-G192
A193: 1.4 | D193: Disbursement #16 - 11/01/2025 | E193: Water Consumption for September and October 2025 Ventanas Meters | F193: 103.9 | G193: 132.92 | H193: =F193-G193
A194: 0.7 | D194: Disbursement #18 - 12/01/2025 | E194: Development Team - DECEMBER 2025 | F194: 14125 | G194: 14125 | H194: =F194-G194
A195: 0.4 | D195: Disbursement #18 - 12/01/2025 | E195: Admin Fee Budget + Financial Controller 25% Salary - DECEMBER 2025 | F195: 3750 | G195: 3750 | H195: =F195-G195
A196: 0.4 | D196: Disbursement #18 - 12/01/2025 | E196: CCSS (Social Security) DECEMBER 2025 | F196: 800 | G196: 800 | H196: =F196-G196
...

Sheet Timeline Detail
A3: Project Category | B3: Phase | C3: WBS NUMBER | D3: Task Title | E3: Budget Revised | F3: YTD Expense | G3: Remaining | H3: Forecast
A4: =IFERROR(INDEX('Job Cost Report'!$E:$E,MATCH($C4,'Job Cost Report'!$B:$B,0)),"") | B4: =IFERROR(INDEX('Job Cost Report'!$F:$F,MATCH($C4,'Job Cost Report'!$B:$B,0)),"") | C4: 0.0001 | D4: =IFERROR(INDEX('Job Cost Report'!$C:$C,MATCH($C4,'Job Cost Report'!$B:$B,0)),"") | E4: =SUMIF('Job Cost Report'!$B:$B,$C4,'Job Cost Report'!$I:$I) | F4: =SUMIF('Job Cost Report'!$B:$B,$C4,'Job Cost Report'!$J:$J) | G4: =SUMIF('Job Cost Report'!$B:$B,$C4,'Job Cost Report'!$K:$K) | H4: =SUMIF('Job Cost Report'!$B:$B,$C4,'Job Cost Report'!$L:$L)
A5: =IFERROR(INDEX('Job Cost Report'!$E:$E,MATCH($C5,'Job Cost Report'!$B:$B,0)),"") | B5: =IFERROR(INDEX('Job Cost Report'!$F:$F,MATCH($C5,'Job Cost Report'!$B:$B,0)),"") | C5: 0.0002 | D5: =IFERROR(INDEX('Job Cost Report'!$C:$C,MATCH($C5,'Job Cost Report'!$B:$B,0)),"") | E5: =SUMIF('Job Cost Report'!$B:$B,$C5,'Job Cost Report'!$I:$I) | F5: =SUMIF('Job Cost Report'!$B:$B,$C5,'Job Cost Report'!$J:$J) | G5: =SUMIF('Job Cost Report'!$B:$B,$C5,'Job Cost Report'!$K:$K) | H5: =SUMIF('Job Cost Report'!$B:$B,$C5,'Job Cost Report'!$L:$L)
A6: =IFERROR(INDEX('Job Cost Report'!$E:$E,MATCH($C6,'Job Cost Report'!$B:$B,0)),"") | B6: =IFERROR(INDEX('Job Cost Report'!$F:$F,MATCH($C6,'Job Cost Report'!$B:$B,0)),"") | C6: 2.1.1 | D6: =IFERROR(INDEX('Job Cost Report'!$C:$C,MATCH($C6,'Job Cost Report'!$B:$B,0)),"") | E6: =SUMIF('Job Cost Report'!$B:$B,$C6,'Job Cost Report'!$I:$I) | F6: =SUMIF('Job Cost Report'!$B:$B,$C6,'Job Cost Report'!$J:$J) | G6: =SUMIF('Job Cost Report'!$B:$B,$C6,'Job Cost Report'!$K:$K) | H6: =SUMIF('Job Cost Report'!$B:$B,$C6,'Job Cost Report'!$L:$L)
A7: =IFERROR(INDEX('Job Cost Report'!$E:$E,MATCH($C7,'Job Cost Report'!$B:$B,0)),"") | B7: =IFERROR(INDEX('Job Cost Report'!$F:$F,MATCH($C7,'Job Cost Report'!$B:$B,0)),"") | C7: 2.1.2 | D7: =IFERROR(INDEX('Job Cost Report'!$C:$C,MATCH($C7,'Job Cost Report'!$B:$B,0)),"") | E7: =SUMIF('Job Cost Report'!$B:$B,$C7,'Job Cost Report'!$I:$I) | F7: =SUMIF('Job Cost Report'!$B:$B,$C7,'Job Cost Report'!$J:$J) | G7: =SUMIF('Job Cost Report'!$B:$B,$C7,'Job Cost Report'!$K:$K) | H7: =SUMIF('Job Cost Report'!$B:$B,$C7,'Job Cost Report'!$L:$L)
A8: =IFERROR(INDEX('Job Cost Report'!$E:$E,MATCH($C8,'Job Cost Report'!$B:$B,0)),"") | B8: =IFERROR(INDEX('Job Cost Report'!$F:$F,MATCH($C8,'Job Cost Report'!$B:$B,0)),"") | C8: 2.1.3 | D8: =IFERROR(INDEX('Job Cost Report'!$C:$C,MATCH($C8,'Job Cost Report'!$B:$B,0)),"") | E8: =SUMIF('Job Cost Report'!$B:$B,$C8,'Job Cost Report'!$I:$I) | F8: =SUMIF('Job Cost Report'!$B:$B,$C8,'Job Cost Report'!$J:$J) | G8: =SUMIF('Job Cost Report'!$B:$B,$C8,'Job Cost Report'!$K:$K) | H8: =SUMIF('Job Cost Report'!$B:$B,$C8,'Job Cost Report'!$L:$L)
A9: =IFERROR(INDEX('Job Cost Report'!$E:$E,MATCH($C9,'Job Cost Report'!$B:$B,0)),"") | B9: =IFERROR(INDEX('Job Cost Report'!$F:$F,MATCH($C9,'Job Cost Report'!$B:$B,0)),"") | C9: 2.1.4 | D9: =IFERROR(INDEX('Job Cost Report'!$C:$C,MATCH($C9,'Job Cost Report'!$B:$B,0)),"") | E9: =SUMIF('Job Cost Report'!$B:$B,$C9,'Job Cost Report'!$I:$I) | F9: =SUMIF('Job Cost Report'!$B:$B,$C9,'Job Cost Report'!$J:$J) | G9: =SUMIF('Job Cost Report'!$B:$B,$C9,'Job Cost Report'!$K:$K) | H9: =SUMIF('Job Cost Report'!$B:$B,$C9,'Job Cost Report'!$L:$L)
A10: =IFERROR(INDEX('Job Cost Report'!$E:$E,MATCH($C10,'Job Cost Report'!$B:$B,0)),"") | B10: =IFERROR(INDEX('Job Cost Report'!$F:$F,MATCH($C10,'Job Cost Report'!$B:$B,0)),"") | C10: 2.2 | D10: =IFERROR(INDEX('Job Cost Report'!$C:$C,MATCH($C10,'Job Cost Report'!$B:$B,0)),"") | E10: =SUMIF('Job Cost Report'!$B:$B,$C10,'Job Cost Report'!$I:$I) | F10: =SUMIF('Job Cost Report'!$B:$B,$C10,'Job Cost Report'!$J:$J) | G10: =SUMIF('Job Cost Report'!$B:$B,$C10,'Job Cost Report'!$K:$K) | H10: =SUMIF('Job Cost Report'!$B:$B,$C10,'Job Cost Report'!$L:$L)
A11: =IFERROR(INDEX('Job Cost Report'!$E:$E,MATCH($C11,'Job Cost Report'!$B:$B,0)),"") | B11: =IFERROR(INDEX('Job Cost Report'!$F:$F,MATCH($C11,'Job Cost Report'!$B:$B,0)),"") | C11: 9.1.1 | D11: =IFERROR(INDEX('Job Cost Report'!$C:$C,MATCH($C11,'Job Cost Report'!$B:$B,0)),"") | E11: =SUMIF('Job Cost Report'!$B:$B,$C11,'Job Cost Report'!$I:$I) | F11: =SUMIF('Job Cost Report'!$B:$B,$C11,'Job Cost Report'!$J:$J) | G11: =SUMIF('Job Cost Report'!$B:$B,$C11,'Job Cost Report'!$K:$K) | H11: =SUMIF('Job Cost Report'!$B:$B,$C11,'Job Cost Report'!$L:$L)
A12: =IFERROR(INDEX('Job Cost Report'!$E:$E,MATCH($C12,'Job Cost Report'!$B:$B,0)),"") | B12: =IFERROR(INDEX('Job Cost Report'!$F:$F,MATCH($C12,'Job Cost Report'!$B:$B,0)),"") | C12: 9.1.2 | D12: =IFERROR(INDEX('Job Cost Report'!$C:$C,MATCH($C12,'Job Cost Report'!$B:$B,0)),"") | E12: =SUMIF('Job Cost Report'!$B:$B,$C12,'Job Cost Report'!$I:$I) | F12: =SUMIF('Job Cost Report'!$B:$B,$C12,'Job Cost Report'!$J:$J) | G12: =SUMIF('Job Cost Report'!$B:$B,$C12,'Job Cost Report'!$K:$K) | H12: =SUMIF('Job Cost Report'!$B:$B,$C12,'Job Cost Report'!$L:$L)
A13: =IFERROR(INDEX('Job Cost Report'!$E:$E,MATCH($C13,'Job Cost Report'!$B:$B,0)),"") | B13: =IFERROR(INDEX('Job Cost Report'!$F:$F,MATCH($C13,'Job Cost Report'!$B:$B,0)),"") | C13: 9.1.3 | D13: =IFERROR(INDEX('Job Cost Report'!$C:$C,MATCH($C13,'Job Cost Report'!$B:$B,0)),"") | E13: =SUMIF('Job Cost Report'!$B:$B,$C13,'Job Cost Report'!$I:$I) | F13: =SUMIF('Job Cost Report'!$B:$B,$C13,'Job Cost Report'!$J:$J) | G13: =SUMIF('Job Cost Report'!$B:$B,$C13,'Job Cost Report'!$K:$K) | H13: =SUMIF('Job Cost Report'!$B:$B,$C13,'Job Cost Report'!$L:$L)
A14: =IFERROR(INDEX('Job Cost Report'!$E:$E,MATCH($C14,'Job Cost Report'!$B:$B,0)),"") | B14: =IFERROR(INDEX('Job Cost Report'!$F:$F,MATCH($C14,'Job Cost Report'!$B:$B,0)),"") | C14: 9.2.1 | D14: =IFERROR(INDEX('Job Cost Report'!$C:$C,MATCH($C14,'Job Cost Report'!$B:$B,0)),"") | E14: =SUMIF('Job Cost Report'!$B:$B,$C14,'Job Cost Report'!$I:$I) | F14: =SUMIF('Job Cost Report'!$B:$B,$C14,'Job Cost Report'!$J:$J) | G14: =SUMIF('Job Cost Report'!$B:$B,$C14,'Job Cost Report'!$K:$K) | H14: =SUMIF('Job Cost Report'!$B:$B,$C14,'Job Cost Report'!$L:$L)
A15: =IFERROR(INDEX('Job Cost Report'!$E:$E,MATCH($C15,'Job Cost Report'!$B:$B,0)),"") | B15: =IFERROR(INDEX('Job Cost Report'!$F:$F,MATCH($C15,'Job Cost Report'!$B:$B,0)),"") | C15: 9.3.1 | D15: =IFERROR(INDEX('Job Cost Report'!$C:$C,MATCH($C15,'Job Cost Report'!$B:$B,0)),"") | E15: =SUMIF('Job Cost Report'!$B:$B,$C15,'Job Cost Report'!$I:$I) | F15: =SUMIF('Job Cost Report'!$B:$B,$C15,'Job Cost Report'!$J:$J) | G15: =SUMIF('Job Cost Report'!$B:$B,$C15,'Job Cost Report'!$K:$K) | H15: =SUMIF('Job Cost Report'!$B:$B,$C15,'Job Cost Report'!$L:$L)
... A80: =IFERROR(INDEX('Job Cost Report'!$E:$E,MATCH($C80,'Job Cost Report'!$B:$B,0)),"") | B80: =IFERROR(INDEX('Job Cost Report'!$F:$F,MATCH($C80,'Job Cost Report'!$B:$B,0)),"") | C80: 7.1 | D80: =IFERROR(INDEX('Job Cost Report'!$C:$C,MATCH($C80,'Job Cost Report'!$B:$B,0)),"") | E80: =SUMIF('Job Cost Report'!$B:$B,$C80,'Job Cost Report'!$I:$I) | F80: =SUMIF('Job Cost Report'!$B:$B,$C80,'Job Cost Report'!$J:$J) | G80: =SUMIF('Job Cost Report'!$B:$B,$C80,'Job Cost Report'!$K:$K) | H80: =SUMIF('Job Cost Report'!$B:$B,$C80,'Job Cost Report'!$L:$L)

Sheet Job Cost Report
A1: DASHBOARD VENTANAS — Job Cost Report
A2: Modelo vivo. Editá el LEDGER y todo recalcula.
N3: Q1 2026 | O3: Q1 2026 | P3: Q1 2026 | Q3: Q1 2026 | R3: Q1 2026 | S3: Q1 2026 | T3: Q1 2026 | U3: Q1 2026 | V3: Q1 2026 | W3: Q1 2026 | X3: Q1 2026 | Y3: Q1 2026 | Z3: Q1 2026 | AA3: Q1 2026 | AB3: Q1 2026 | AC3: Q1 2026 | AD3: Q1 2026 | AE3: Q2 2026 | AF3: Q2 2026 | AG3: Q2 2026 | AH3: Q2 2026 | AI3: Q2 2026 | AJ3: Q2 2026 | AK3: Q2 2026 | AL3: Q2 2026 | AM3: Q2 2026 | AN3: Q2 2026 | AO3: Q2 2026 | AP3: Q2 2026 | AQ3: Q2 2026 | AR3: Q2 2026 | AS3: Q2 2026 | AT3: Q2 2026 | AU3: Q2 2026 | AV3: Q3 2026 | AW3: Q3 2026 | AX3: Q3 2026 | AY3: Q3 2026 | AZ3: Q3 2026 | BA3: Q3 2026 | BB3: Q3 2026 | BC3: Q3 2026 | BD3: Q3 2026 | BE3: Q3 2026 | BF3: Q3 2026 | BG3: Q3 2026 | BH3: Q3 2026 | BI3: Q3 2026 | BJ3: Q3 2026 | BK3: Q3 2026 | BL3: Q3 2026 | BM3: Q4 2026 | BN3: Q4 2026 | BO3: Q4 2026 | BP3: Q4 2026 | BQ3: Q4 2026 | BR3: Q4 2026 | BS3: Q4 2026 | BT3: Q4 2026 | BU3: Q4 2026 | BV3: Q4 2026 | BW3: Q4 2026 | BX3: Q4 2026 | BY3: Q4 2026 | BZ3: Q4 2026 | CA3: Q4 2026 | CB3: Q4 2026 | CC3: Q4 2026
N4: JAN 2026 | O4: JAN 2026 | P4: JAN 2026 | Q4: JAN 2026 | R4: MES | S4: FEB 2026 | T4: FEB 2026 | U4: FEB 2026 | V4: FEB 2026 | W4: MES | X4: MAR 2026 | Y4: MAR 2026 | Z4: MAR 2026 | AA4: MAR 2026 | AB4: MAR 2026 | AC4: MES | AD4: TRIMESTRE | AE4: APR 2026 | AF4: APR 2026 | AG4: APR 2026 | AH4: APR 2026 | AI4: MES | AJ4: MAY 2026 | AK4: MAY 2026 | AL4: MAY 2026 | AM4: MAY 2026 | AN4: MES | AO4: JUN 2026 | AP4: JUN 2026 | AQ4: JUN 2026 | AR4: JUN 2026 | AS4: JUN 2026 | AT4: MES | AU4: TRIMESTRE | AV4: JUL 2026 | AW4: JUL 2026 | AX4: JUL 2026 | AY4: JUL 2026 | AZ4: MES | BA4: AUG 2026 | BB4: AUG 2026 | BC4: AUG 2026 | BD4: AUG 2026 | BE4: AUG 2026 | BF4: MES | BG4: SEP 2026 | BH4: SEP 2026 | BI4: SEP 2026 | BJ4: SEP 2026 | BK4: MES | BL4: TRIMESTRE | BM4: OCT 2026 | BN4: OCT 2026 | BO4: OCT 2026 | BP4: OCT 2026 | BQ4: MES | BR4: NOV 2026 | BS4: NOV 2026 | BT4: NOV 2026 | BU4: NOV 2026 | BV4: NOV 2026 | BW4: MES | BX4: DEC 2026 | BY4: DEC 2026 | BZ4: DEC 2026 | CA4: DEC 2026 | CB4: MES | CC4: TRIMESTRE
A5: Status | B5: WBS | C5: Task Title | D5: Owner | E5: Category | F5: Phase | G5: Budget Original | H5: Budget Change | I5: Budget Revised | J5: Spend | K5: Remaining | L5: Forecast | M5: Variance | N5: 5 | O5: 12 | P5: 19 | Q5: 26 | R5: JAN | S5: 2 | T5: 9 | U5: 16 | V5: 23 | W5: FEB | X5: 2 | Y5: 9 | Z5: 16 | AA5: 23 | AB5: 30 | AC5: MAR | AD5: Q1 2026 | AE5: 6 | AF5: 13 | AG5: 20 | AH5: 27 | AI5: APR | AJ5: 4 | AK5: 11 | AL5: 18 | AM5: 25 | AN5: MAY | AO5: 1 | AP5: 8 | AQ5: 15 | AR5: 22 | AS5: 29 | AT5: JUN | AU5: Q2 2026 | AV5: 6 | AW5: 13 | AX5: 20 | AY5: 27 | AZ5: JUL | BA5: 3 | BB5: 10 | BC5: 17 | BD5: 24 | BE5: 31 | BF5: AUG | BG5: 7 | BH5: 14 | BI5: 21 | BJ5: 28 | BK5: SEP | BL5: Q3 2026 | BM5: 5 | BN5: 12 | BO5: 19 | BP5: 26 | BQ5: OCT | BR5: 2 | BS5: 9 | BT5: 16 | BU5: 23 | BV5: 30 | BW5: NOV | BX5: 7 | BY5: 14 | BZ5: 21 | CA5: 28 | CB5: DEC | CC5: Q4 2026 | CD5: TOTAL
C6: TOTAL <object object at 0x7f16e877ac70>
A7: 0-PROPERTY ACQUISITION
A8: Completed | B8: 0.0001 | C8: Due Diligence / Closing Costs | D8: HOVDE | E8: 0-Property Acquisition | F8: Phase 1 | G8: 388000 | H8: 415720.07 | I8: =G8+H8 | J8: =SUMIF(LEDGER!$A:$A,$B8,LEDGER!$G:$G) | K8: =I8-J8 | L8: =J8+CD8 | M8: =I8-L8 | R8: =SUM(N8:Q8) | W8: =SUM(S8:V8) | AC8: =SUM(X8:AB8) | AD8: =R8+W8+AC8 | AI8: =SUM(AE8:AH8) | AN8: =SUM(AJ8:AM8) | AT8: =SUM(AO8:AS8) | AU8: =AI8+AN8+AT8 | AZ8: =SUM(AV8:AY8) | BF8: =SUM(BA8:BE8) | BK8: =SUM(BG8:BJ8) | BL8: =AZ8+BF8+BK8 | BQ8: =SUM(BM8:BP8) | BW8: =SUM(BR8:BV8) | CB8: =SUM(BX8:CA8) | CC8: =BQ8+BW8+CB8 | CD8: =AD8+AU8+BL8+CC8
A9: In process | B9: 0.0002 | C9: Property Acquisition | D9: Partnership | E9: 0-Property Acquisition | F9: Phase 1 | G9: 11250000 | H9: 0 | I9: =G9+H9 | J9: =SUMIF(LEDGER!$A:$A,$B9,LEDGER!$G:$G) | K9: =I9-J9 | L9: =J9+CD9 | M9: =I9-L9 | R9: =SUM(N9:Q9) | W9: =SUM(S9:V9) | AC9: =SUM(X9:AB9) | AD9: =R9+W9+AC9 | AI9: =SUM(AE9:AH9) | AN9: =SUM(AJ9:AM9) | AT9: =SUM(AO9:AS9) | AU9: =AI9+AN9+AT9 | AZ9: =SUM(AV9:AY9) | BF9: =SUM(BA9:BE9) | BJ9: 1875000 | BK9: =SUM(BG9:BJ9) | BL9: =AZ9+BF9+BK9 | BQ9: =SUM(BM9:BP9) | BW9: =SUM(BR9:BV9) | CB9: =SUM(BX9:CA9) | CC9: =BQ9+BW9+CB9 | CD9: =AD9+AU9+BL9+CC9
C10: TOTAL 0-Property Acquisition | G10: =G8+G9 | H10: =H8+H9 | I10: =I8+I9 | J10: =J8+J9 | K10: =K8+K9 | L10: =L8+L9 | M10: =M8+M9 | R10: =R8+R9 | W10: =W8+W9 | AC10: =AC8+AC9 | AD10: =AD8+AD9 | AI10: =AI8+AI9 | AN10: =AN8+AN9 | AT10: =AT8+AT9 | AU10: =AU8+AU9 | AZ10: =AZ8+AZ9 | BF10: =BF8+BF9 | BK10: =BK8+BK9 | BL10: =BL8+BL9 | BQ10: =BQ8+BQ9 | BW10: =BW8+BW9 | CB10: =CB8+CB9 | CC10: =CC8+CC9 | CD10: =CD8+CD9
A11: CFIA CONDO
A12: In process | B12: 2.1.1 | C12: Pre Workshop | D12: EDSA | E12: CFIA Condo | F12: DESIGN | G12: 14500 | H12: 0 | I12: =G12+H12 | J12: =SUMIF(LEDGER!$A:$A,$B12,LEDGER!$G:$G) | K12: =I12-J12 | L12: =J12+CD12 | M12: =I12-L12 | R12: =SUM(N12:Q12) | W12: =SUM(S12:V12) | AC12: =SUM(X12:AB12) | AD12: =R12+W12+AC12 | AE12: 14500 | AI12: =SUM(AE12:AH12) | AN12: =SUM(AJ12:AM12) | AT12: =SUM(AO12:AS12) | AU12: =AI12+AN12+AT12 | AZ12: =SUM(AV12:AY12) | BF12: =SUM(BA12:BE12) | BK12: =SUM(BG12:BJ12) | BL12: =AZ12+BF12+BK12 | BQ12: =SUM(BM12:BP12) | BW12: =SUM(BR12:BV12) | CB12: =SUM(BX12:CA12) | CC12: =BQ12+BW12+CB12 | CD12: =AD12+AU12+BL12+CC12
A13: Approved | B13: 2.1.2 | C13: Workshop | D13: EDSA | E13: CFIA Condo | F13: DESIGN | G13: 24500 | H13: 29631.6 | I13: =G13+H13 | J13: =SUMIF(LEDGER!$A:$A,$B13,LEDGER!$G:$G) | K13: =I13-J13 | L13: =J13+CD13 | M13: =I13-L13 | R13: =SUM(N13:Q13) | W13: =SUM(S13:V13) | AC13: =SUM(X13:AB13) | AD13: =R13+W13+AC13 | AI13: =SUM(AE13:AH13) | AN13: =SUM(AJ13:AM13) | AT13: =SUM(AO13:AS13) | AU13: =AI13+AN13+AT13 | AZ13: =SUM(AV13:AY13) | BF13: =SUM(BA13:BE13) | BK13: =SUM(BG13:BJ13) | BL13: =AZ13+BF13+BK13 | BQ13: =SUM(BM13:BP13) | BW13: =SUM(BR13:BV13) | CB13: =SUM(BX13:CA13) | CC13: =BQ13+BW13+CB13 | CD13: =AD13+AU13+BL13+CC13
A14: Approved | B14: 2.1.3 | C14: Post Workshop / Conceptual Enlargements | D14: EDSA | E14: CFIA Condo | F14: DESIGN | G14: 48500 | H14: 0 | I14: =G14+H14 | J14: =SUMIF(LEDGER!$A:$A,$B14,LEDGER!$G:$G) | K14: =I14-J14 | L14: =J14+CD14 | M14: =I14-L14 | R14: =SUM(N14:Q14) | W14: =SUM(S14:V14) | AC14: =SUM(X14:AB14) | AD14: =R14+W14+AC14 | AI14: =SUM(AE14:AH14) | AN14: =SUM(AJ14:AM14) | AO14: 41000 | AT14: =SUM(AO14:AS14) | AU14: =AI14+AN14+AT14 | AZ14: =SUM(AV14:AY14) | BF14: =SUM(BA14:BE14) | BK14: =SUM(BG14:BJ14) | BL14: =AZ14+BF14+BK14 | BQ14: =SUM(BM14:BP14) | BW14: =SUM(BR14:BV14) | CB14: =SUM(BX14:CA14) | CC14: =BQ14+BW14+CB14 | CD14: =AD14+AU14+BL14+CC14
A15: Approved | B15: 2.1.4 | C15: Travel Expenses MP | D15: EDSA | E15: CFIA Condo | F15: DESIGN | G15: 5000 | H15: 0 | I15: =G15+H15 | J15: =SUMIF(LEDGER!$A:$A,$B15,LEDGER!$G:$G) | K15: =I15-J15 | L15: =J15+CD15 | M15: =I15-L15 | R15: =SUM(N15:Q15) | W15: =SUM(S15:V15) | AC15: =SUM(X15:AB15) | AD15: =R15+W15+AC15 | AI15: =SUM(AE15:AH15) | AN15: =SUM(AJ15:AM15) | AT15: =SUM(AO15:AS15) | AU15: =AI15+AN15+AT15 | AZ15: =SUM(AV15:AY15) | BA15: 5000 | BF15: =SUM(BA15:BE15) | BK15: =SUM(BG15:BJ15) | BL15: =AZ15+BF15+BK15 | BQ15: =SUM(BM15:BP15) | BW15: =SUM(BR15:BV15) | CB15: =SUM(BX15:CA15) | CC15: =BQ15+BW15+CB15 | CD15: =AD15+AU15+BL15+CC15
A16: Approved | B16: 2.2 | C16: Schematic Design | D16: EDSA | E16: CFIA Condo | F16: DESIGN | G16: 100000 | H16: 0 | I16: =G16+H16 | J16: =SUMIF(LEDGER!$A:$A,$B16,LEDGER!$G:$G) | K16: =I16-J16 | L16: =J16+CD16 | M16: =I16-L16 | R16: =SUM(N16:Q16) | W16: =SUM(S16:V16) | AC16: =SUM(X16:AB16) | AD16: =R16+W16+AC16 | AI16: =SUM(AE16:AH16) | AN16: =SUM(AJ16:AM16) | AT16: =SUM(AO16:AS16) | AU16: =AI16+AN16+AT16 | AZ16: =SUM(AV16:AY16) | BF16: =SUM(BA16:BE16) | BG16: 25000 | BH16: 25000 | BI16: 25000 | BJ16: 25000 | BK16: =SUM(BG16:BJ16) | BL16: =AZ16+BF16+BK16 | BQ16: =SUM(BM16:BP16) | BW16: =SUM(BR16:BV16) | CB16: =SUM(BX16:CA16) | CC16: =BQ16+BW16+CB16 | CD16: =AD16+AU16+BL16+CC16
C17: TOTAL CFIA Condo | G17: =G12+G13+G14+G15+G16 | H17: =H12+H13+H14+H15+H16 | I17: =I12+I13+I14+I15+I16 | J17: =J12+J13+J14+J15+J16 | K17: =K12+K13+K14+K15+K16 | L17: =L12+L13+L14+L15+L16 | M17: =M12+M13+M14+M15+M16 | R17: =R12+R13+R14+R15+R16 | W17: =W12+W13+W14+W15+W16 | AC17: =AC12+AC13+AC14+AC15+AC16 | AD17: =AD12+AD13+AD14+AD15+AD16 | AI17: =AI12+AI13+AI14+AI15+AI16 | AN17: =AN12+AN13+AN14+AN15+AN16 | AT17: =AT12+AT13+AT14+AT15+AT16 | AU17: =AU12+AU13+AU14+AU15+AU16 | AZ17: =AZ12+AZ13+AZ14+AZ15+AZ16 | BF17: =BF12+BF13+BF14+BF15+BF16 | BK17: =BK12+BK13+BK14+BK15+BK16 | BL17: =BL12+BL13+BL14+BL15+BL16 | BQ17: =BQ12+BQ13+BQ14+BQ15+BQ16 | BW17: =BW12+BW13+BW14+BW15+BW16 | CB17: =CB12+CB13+CB14+CB15+CB16 | CC17: =CC12+CC13+CC14+CC15+CC16 | CD17: =CD12+CD13+CD14+CD15+CD16
A18: CFIA INFRASTRUCTURE
A19: In process | B19: 9.1.1 | C19: Phase 1/2/3 Pre Consultations | D19: DEHC | E19: CFIA Infrastructure | F19: Phase 1 | G19: 0 | H19: 5424 | I19: =G19+H19 | J19: =SUMIF(LEDGER!$A:$A,$B19,LEDGER!$G:$G) | K19: =I19-J19 | L19: =J19+CD19 | M19: =I19-L19 | R19: =SUM(N19:Q19) | S19: -1921 | W19: =SUM(S19:V19) | AC19: =SUM(X19:AB19) | AD19: =R19+W19+AC19 | AI19: =SUM(AE19:AH19) | AN19: =SUM(AJ19:AM19) | AT19: =SUM(AO19:AS19) | AU19: =AI19+AN19+AT19 | AZ19: =SUM(AV19:AY19) | BF19: =SUM(BA19:BE19) | BK19: =SUM(BG19:BJ19) | BL19: =AZ19+BF19+BK19 | BQ19: =SUM(BM19:BP19) | BW19: =SUM(BR19:BV19) | CB19: =SUM(BX19:CA19) | CC19: =BQ19+BW19+CB19 | CD19: =AD19+AU19+BL19+CC19
A20: In process | B20: 9.1.2 | C20: Phase 1/2/3 Discharge permit MOPT and Municipality | D20: DEHC | E20: CFIA Infrastructure | F20: Phase 2 | G20: 0 | H20: 1356 | I20: =G20+H20 | J20: =SUMIF(LEDGER!$A:$A,$B20,LEDGER!$G:$G) | K20: =I20-J20 | L20: =J20+CD20 | M20: =I20-L20 | R20: =SUM(N20:Q20) | S20: -678 | W20: =SUM(S20:V20) | AC20: =SUM(X20:AB20) | AD20: =R20+W20+AC20 | AI20: =SUM(AE20:AH20) | AN20: =SUM(AJ20:AM20) | AT20: =SUM(AO20:AS20) | AU20: =AI20+AN20+AT20 | AZ20: =SUM(AV20:AY20) | BF20: =SUM(BA20:BE20) | BK20: =SUM(BG20:BJ20) | BL20: =AZ20+BF20+BK20 | BQ20: =SUM(BM20:BP20) | BW20: =SUM(BR20:BV20) | CB20: =SUM(BX20:CA20) | CC20: =BQ20+BW20+CB20 | CD20: =AD20+AU20+BL20+CC20
A21: Approved | B21: 9.1.3 | C21: Phase 1 Permit (Includes topo of the existing road) | D21: DEHC | E21: CFIA Infrastructure | F21: Phase 1 | G21: 0 | H21: 16385 | I21: =G21+H21 | J21: =SUMIF(LEDGER!$A:$A,$B21,LEDGER!$G:$G) | K21: =I21-J21 | L21: =J21+CD21 | M21: =I21-L21 | R21: =SUM(N21:Q21) | W21: =SUM(S21:V21) | AC21: =SUM(X21:AB21) | AD21: =R21+W21+AC21 | AI21: =SUM(AE21:AH21) | AN21: =SUM(AJ21:AM21) | AT21: =SUM(AO21:AS21) | AU21: =AI21+AN21+AT21 | AZ21: =SUM(AV21:AY21) | BF21: =SUM(BA21:BE21) | BK21: =SUM(BG21:BJ21) | BL21: =AZ21+BF21+BK21 | BQ21: =SUM(BM21:BP21) | BW21: =SUM(BR21:BV21) | CB21: =SUM(BX21:CA21) | CC21: =BQ21+BW21+CB21 | CD21: =AD21+AU21+BL21+CC21
A22: Approved | B22: 9.2.1 | C22: Phase 2 Permit | D22: DEHC | E22: CFIA Infrastructure | F22: Phase 2 | G22: 0 | H22: 8814 | I22: =G22+H22 | J22: =SUMIF(LEDGER!$A:$A,$B22,LEDGER!$G:$G) | K22: =I22-J22 | L22: =J22+CD22 | M22: =I22-L22 | R22: =SUM(N22:Q22) | W22: =SUM(S22:V22) | AA22: 8814 | AC22: =SUM(X22:AB22) | AD22: =R22+W22+AC22 | AI22: =SUM(AE22:AH22) | AN22: =SUM(AJ22:AM22) | AT22: =SUM(AO22:AS22) | AU22: =AI22+AN22+AT22 | AZ22: =SUM(AV22:AY22) | BF22: =SUM(BA22:BE22) | BK22: =SUM(BG22:BJ22) | BL22: =AZ22+BF22+BK22 | BQ22: =SUM(BM22:BP22) | BW22: =SUM(BR22:BV22) | CB22: =SUM(BX22:CA22) | CC22: =BQ22+BW22+CB22 | CD22: =AD22+AU22+BL22+CC22
A23: Approved | B23: 9.3.1 | C23: Phase 3 Permit | D23: DEHC | E23: CFIA Infrastructure | F23: Phase 3 | G23: 0 | H23: 1356 | I23: =G23+H23 | J23: =SUMIF(LEDGER!$A:$A,$B23,LEDGER!$G:$G) | K23: =I23-J23 | L23: =J23+CD23 | M23: =I23-L23 | R23: =SUM(N23:Q23) | W23: =SUM(S23:V23) | AA23: 1356 | AC23: =SUM(X23:AB23) | AD23: =R23+W23+AC23 | AI23: =SUM(AE23:AH23) | AN23: =SUM(AJ23:AM23) | AT23: =SUM(AO23:AS23) | AU23: =AI23+AN23+AT23 | AZ23: =SUM(AV23:AY23) | BF23: =SUM(BA23:BE23) | BK23: =SUM(BG23:BJ23) | BL23: =AZ23+BF23+BK23 | BQ23: =SUM(BM23:BP23) | BW23: =SUM(BR23:BV23) | CB23: =SUM(BX23:CA23) | CC23: =BQ23+BW23+CB23 | CD23: =AD23+AU23+BL23+CC23
A24: Approved | B24: 7.2 | C24: Plan and approval of the two condominiums | D24: Blake | E24: CFIA Infrastructure | F24: Phase 3 | G24: 0 | H24: 0 | I24: =G24+H24 | J24: =SUMIF(LEDGER!$A:$A,$B24,LEDGER!$G:$G) | K24: =I24-J24 | L24: =J24+CD24 | M24: =I24-L24 | R24: =SUM(N24:Q24) | W24: =SUM(S24:V24) | AC24: =SUM(X24:AB24) | AD24: =R24+W24+AC24 | AI24: =SUM(AE24:AH24) | AN24: =SUM(AJ24:AM24) | AT24: =SUM(AO24:AS24) | AU24: =AI24+AN24+AT24 | AZ24: =SUM(AV24:AY24) | BF24: =SUM(BA24:BE24) | BK24: =SUM(BG24:BJ24) | BL24: =AZ24+BF24+BK24 | BQ24: =SUM(BM24:BP24) | BW24: =SUM(BR24:BV24) | CB24: =SUM(BX24:CA24) | CC24: =BQ24+BW24+CB24 | CD24: =AD24+AU24+BL24+CC24
A25: Approved | B25: 7.3 | C25: Cadastre Plan (only when we want to convey) | D25: Surveyor | E25: CFIA Infrastructure | F25: Phase 3 | G25: 102162.45 | H25: 0 | I25: =G25+H25 | J25: =SUMIF(LEDGER!$A:$A,$B25,LEDGER!$G:$G) | K25: =I25-J25 | L25: =J25+CD25 | M25: =I25-L25 | R25: =SUM(N25:Q25) | W25: =SUM(S25:V25) | AC25: =SUM(X25:AB25) | AD25: =R25+W25+AC25 | AI25: =SUM(AE25:AH25) | AJ25: 51081.22 | AN25: =SUM(AJ25:AM25) | AT25: =SUM(AO25:AS25) | AU25: =AI25+AN25+AT25 | AZ25: =SUM(AV25:AY25) | BF25: =SUM(BA25:BE25) | BG25: 51081.22 | BK25: =SUM(BG25:BJ25) | BL25: =AZ25+BF25+BK25 | BQ25: =SUM(BM25:BP25) | BW25: =SUM(BR25:BV25) | CB25: =SUM(BX25:CA25) | CC25: =BQ25+BW25+CB25 | CD25: =AD25+AU25+BL25+CC25
A26: Approved | B26: 7.4 | C26: CFIA (1%) - Whole Project | D26: Blake | E26: CFIA Infrastructure | F26: Phase 3 | G26: 265000 | H26: 0 | I26: =G26+H26 | J26: =SUMIF(LEDGER!$A:$A,$B26,LEDGER!$G:$G) | K26: =I26-J26 | L26: =J26+CD26 | M26: =I26-L26 | R26: =SUM(N26:Q26) | W26: =SUM(S26:V26) | AC26: =SUM(X26:AB26) | AD26: =R26+W26+AC26 | AI26: =SUM(AE26:AH26) | AN26: =SUM(AJ26:AM26) | AT26: =SUM(AO26:AS26) | AU26: =AI26+AN26+AT26 | AZ26: =SUM(AV26:AY26) | BA26: 265000 | BF26: =SUM(BA26:BE26) | BK26: =SUM(BG26:BJ26) | BL26: =AZ26+BF26+BK26 | BQ26: =SUM(BM26:BP26) | BW26: =SUM(BR26:BV26) | CB26: =SUM(BX26:CA26) | CC26: =BQ26+BW26+CB26 | CD26: =AD26+AU26+BL26+CC26
A27: Approved | B27: 7.5 | C27: INS (1.298%) - Phase Only | D27: Blake | E27: CFIA Infrastructure | F27: Phase 3 | G27: 129800 | H27: 0 | I27: =G27+H27 | J27: =SUMIF(LEDGER!$A:$A,$B27,LEDGER!$G:$G) | K27: =I27-J27 | L27: =J27+CD27 | M27: =I27-L27 | R27: =SUM(N27:Q27) | W27: =SUM(S27:V27) | AC27: =SUM(X27:AB27) | AD27: =R27+W27+AC27 | AI27: =SUM(AE27:AH27) | AN27: =SUM(AJ27:AM27) | AT27: =SUM(AO27:AS27) | AU27: =AI27+AN27+AT27 | AZ27: =SUM(AV27:AY27) | BF27: =SUM(BA27:BE27) | BK27: =SUM(BG27:BJ27) | BL27: =AZ27+BF27+BK27 | BQ27: =SUM(BM27:BP27) | BU27: 129800 | BW27: =SUM(BR27:BV27) | CB27: =SUM(BX27:CA27) | CC27: =BQ27+BW27+CB27 | CD27: =AD27+AU27+BL27+CC27
A28: Approved | B28: 7.6 | C28: SETENA Bond (1.5% Value) - Phase Only | D28: Partnership | E28: CFIA Infrastructure | F28: Phase 3 | G28: 300000 | H28: 0 | I28: =G28+H28 | J28: =SUMIF(LEDGER!$A:$A,$B28,LEDGER!$G:$G) | K28: =I28-J28 | L28: =J28+CD28 | M28: =I28-L28 | R28: =SUM(N28:Q28) | W28: =SUM(S28:V28) | AC28: =SUM(X28:AB28) | AD28: =R28+W28+AC28 | AI28: =SUM(AE28:AH28) | AN28: =SUM(AJ28:AM28) | AT28: =SUM(AO28:AS28) | AU28: =AI28+AN28+AT28 | AZ28: =SUM(AV28:AY28) | BF28: =SUM(BA28:BE28) | BK28: =SUM(BG28:BJ28) | BL28: =AZ28+BF28+BK28 | BQ28: =SUM(BM28:BP28) | BR28: 300000 | BW28: =SUM(BR28:BV28) | CB28: =SUM(BX28:CA28) | CC28: =BQ28+BW28+CB28 | CD28: =AD28+AU28+BL28+CC28
A29: Approved | B29: 7.7 | C29: Municipality (1%) - Phase Only | D29: Permit Engineer | E29: CFIA Infrastructure | F29: Phase 3 | G29: 100000 | H29: 0 | I29: =G29+H29 | J29: =SUMIF(LEDGER!$A:$A,$B29,LEDGER!$G:$G) | K29: =I29-J29 | L29: =J29+CD29 | M29: =I29-L29 | R29: =SUM(N29:Q29) | W29: =SUM(S29:V29) | AC29: =SUM(X29:AB29) | AD29: =R29+W29+AC29 | AI29: =SUM(AE29:AH29) | AN29: =SUM(AJ29:AM29) | AT29: =SUM(AO29:AS29) | AU29: =AI29+AN29+AT29 | AZ29: =SUM(AV29:AY29) | BF29: =SUM(BA29:BE29) | BK29: =SUM(BG29:BJ29) | BL29: =AZ29+BF29+BK29 | BQ29: =SUM(BM29:BP29) | BW29: =SUM(BR29:BV29) | BX29: 100000 | CB29: =SUM(BX29:CA29) | CC29: =BQ29+BW29+CB29 | CD29: =AD29+AU29+BL29+CC29
C30: TOTAL CFIA Infrastructure | G30: =G19+G20+G21+G22+G23+G24+G25+G26+G27+G28+G29 | H30: =H19+H20+H21+H22+H23+H24+H25+H26+H27+H28+H29 | I30: =I19+I20+I21+I22+I23+I24+I25+I26+I27+I28+I29 | J30: =J19+J20+J21+J22+J23+J24+J25+J26+J27+J28+J29 | K30: =K19+K20+K21+K22+K23+K24+K25+K26+K27+K28+K29 | L30: =L19+L20+L21+L22+L23+L24+L25+L26+L27+L28+L29 | M30: =M19+M20+M21+M22+M23+M24+M25+M26+M27+M28+M29 | R30: =R19+R20+R21+R22+R23+R24+R25+R26+R27+R28+R29 | W30: =W19+W20+W21+W22+W23+W24+W25+W26+W27+W28+W29 | AC30: =AC19+AC20+AC21+AC22+AC23+AC24+AC25+AC26+AC27+AC28+AC29 | AD30: =AD19+AD20+AD21+AD22+AD23+AD24+AD25+AD26+AD27+AD28+AD29 | AI30: =AI19+AI20+AI21+AI22+AI23+AI24+AI25+AI26+AI27+AI28+AI29 | AN30: =AN19+AN20+AN21+AN22+AN23+AN24+AN25+AN26+AN27+AN28+AN29 | AT30: =AT19+AT20+AT21+AT22+AT23+AT24+AT25+AT26+AT27+AT28+AT29 | AU30: =AU19+AU20+AU21+AU22+AU23+AU24+AU25+AU26+AU27+AU28+AU29 | AZ30: =AZ19+AZ20+AZ21+AZ22+AZ23+AZ24+AZ25+AZ26+AZ27+AZ28+AZ29 | BF30: =BF19+BF20+BF21+BF22+BF23+BF24+BF25+BF26+BF27+BF28+BF29 | BK30: =BK19+BK20+BK21+BK22+BK23+BK24+BK25+BK26+BK27+BK28+BK29 | BL30: =BL19+BL20+BL21+BL22+BL23+BL24+BL25+BL26+BL27+BL28+BL29 | BQ30: =BQ19+BQ20+BQ21+BQ22+BQ23+BQ24+BQ25+BQ26+BQ27+BQ28+BQ29 | BW30: =BW19+BW20+BW21+BW22+BW23+BW24+BW25+BW26+BW27+BW28+BW29 | CB30: =CB19+CB20+CB21+CB22+CB23+CB24+CB25+CB26+CB27+CB28+CB29 | CC30: =CC19+CC20+CC21+CC22+CC23+CC24+CC25+CC26+CC27+CC28+CC29 | CD30: =CD19+CD20+CD21+CD22+CD23+CD24+CD25+CD26+CD27+CD28+CD29
A31: CONCESSIONS
A32: In process | B32: 5.1 | C32: Preliminar Study for PNE applications in ACOSA, SINAC, and Muni | D32: Eduardo | E32: Concessions | F32: SETENA Regional Review | G32: 0 | H32: 5000 | I32: =G32+H32 | J32: =SUMIF(LEDGER!$A:$A,$B32,LEDGER!$G:$G) | K32: =I32-J32 | L32: =J32+CD32 | M32: =I32-L32 | R32: =SUM(N32:Q32) | W32: =SUM(S32:V32) | AC32: =SUM(X32:AB32) | AD32: =R32+W32+AC32 | AI32: =SUM(AE32:AH32) | AN32: =SUM(AJ32:AM32) | AT32: =SUM(AO32:AS32) | AU32: =AI32+AN32+AT32 | AZ32: =SUM(AV32:AY32) | BF32: =SUM(BA32:BE32) | BK32: =SUM(BG32:BJ32) | BL32: =AZ32+BF32+BK32 | BM32: 5000 | BQ32: =SUM(BM32:BP32) | BW32: =SUM(BR32:BV32) | CB32: =SUM(BX32:CA32) | CC32: =BQ32+BW32+CB32 | CD32: =AD32+AU32+BL32+CC32
A33: In process | B33: 5.2 | C33: Engineering diagnosis to apply reversion of Patrimony areas to Muni ( to apply later for concessions ) | D33: Eduardo consultant | E33: Concessions | F33: SETENA Regional Review | G33: 9944 | H33: 0 | I33: =G33+H33 | J33: =SUMIF(LEDGER!$A:$A,$B33,LEDGER!$G:$G) | K33: =I33-J33 | L33: =J33+CD33 | M33: =I33-L33 | R33: =SUM(N33:Q33) | W33: =SUM(S33:V33) | AA33: 4972 | AC33: =SUM(X33:AB33) | AD33: =R33+W33+AC33 | AI33: =SUM(AE33:AH33) | AN33: =SUM(AJ33:AM33) | AT33: =SUM(AO33:AS33) | AU33: =AI33+AN33+AT33 | AZ33: =SUM(AV33:AY33) | BF33: =SUM(BA33:BE33) | BK33: =SUM(BG33:BJ33) | BL33: =AZ33+BF33+BK33 | BM33: 4972 | BQ33: =SUM(BM33:BP33) | BW33: =SUM(BR33:BV33) | CB33: =SUM(BX33:CA33) | CC33: =BQ33+BW33+CB33 | CD33: =AD33+AU33+BL33+CC33
A34: Approved | B34: 5.3 | C34: Application/ project description for PNE MINAET | D34: Eduardo | E34: Concessions | F34: SETENA Regional Review | G34: 15876.5 | H34: 0 | I34: =G34+H34 | J34: =SUMIF(LEDGER!$A:$A,$B34,LEDGER!$G:$G) | K34: =I34-J34 | L34: =J34+CD34 | M34: =I34-L34 | R34: =SUM(N34:Q34) | W34: =SUM(S34:V34) | AC34: =SUM(X34:AB34) | AD34: =R34+W34+AC34 | AI34: =SUM(AE34:AH34) | AJ34: 15876.5 | AN34: =SUM(AJ34:AM34) | AT34: =SUM(AO34:AS34) | AU34: =AI34+AN34+AT34 | AZ34: =SUM(AV34:AY34) | BF34: =SUM(BA34:BE34) | BK34: =SUM(BG34:BJ34) | BL34: =AZ34+BF34+BK34 | BQ34: =SUM(BM34:BP34) | BW34: =SUM(BR34:BV34) | CB34: =SUM(BX34:CA34) | CC34: =BQ34+BW34+CB34 | CD34: =AD34+AU34+BL34+CC34
A35: Approved | B35: 5.4 | C35: Survey new plans - Adjust to Government Regs | D35: Surveyor | E35: Concessions | F35: SETENA Regional Review | G35: 72207 | H35: 0 | I35: =G35+H35 | J35: =SUMIF(LEDGER!$A:$A,$B35,LEDGER!$G:$G) | K35: =I35-J35 | L35: =J35+CD35 | M35: =I35-L35 | R35: =SUM(N35:Q35) | W35: =SUM(S35:V35) | AC35: =SUM(X35:AB35) | AD35: =R35+W35+AC35 | AH35: 16950 | AI35: =SUM(AE35:AH35) | AN35: =SUM(AJ35:AM35) | AO35: 30000 | AT35: =SUM(AO35:AS35) | AU35: =AI35+AN35+AT35 | AV35: 16950 | AY35: 8307 | AZ35: =SUM(AV35:AY35) | BF35: =SUM(BA35:BE35) | BK35: =SUM(BG35:BJ35) | BL35: =AZ35+BF35+BK35 | BQ35: =SUM(BM35:BP35) | BW35: =SUM(BR35:BV35) | CB35: =SUM(BX35:CA35) | CC35: =BQ35+BW35+CB35 | CD35: =AD35+AU35+BL35+CC35
A36: Approved | B36: 5.5 | C36: Create Draft Plans for Development | D36: Randall | E36: Concessions | F36: SETENA Regional Review | G36: 30000 | H36: 0 | I36: =G36+H36 | J36: =SUMIF(LEDGER!$A:$A,$B36,LEDGER!$G:$G) | K36: =I36-J36 | L36: =J36+CD36 | M36: =I36-L36 | R36: =SUM(N36:Q36) | W36: =SUM(S36:V36) | AC36: =SUM(X36:AB36) | AD36: =R36+W36+AC36 | AI36: =SUM(AE36:AH36) | AN36: =SUM(AJ36:AM36) | AO36: 15000 | AT36: =SUM(AO36:AS36) | AU36: =AI36+AN36+AT36 | AX36: 15000 | AZ36: =SUM(AV36:AY36) | BF36: =SUM(BA36:BE36) | BK36: =SUM(BG36:BJ36) | BL36: =AZ36+BF36+BK36 | BQ36: =SUM(BM36:BP36) | BW36: =SUM(BR36:BV36) | CB36: =SUM(BX36:CA36) | CC36: =BQ36+BW36+CB36 | CD36: =AD36+AU36+BL36+CC36
A37: In process | B37: 5.6 | C37: Legal Expenses - Concession MUNI | D37: Herbet | E37: Concessions | F37: SETENA Regional Review | G37: 100000 | H37: 0 | I37: =G37+H37 | J37: =SUMIF(LEDGER!$A:$A,$B37,LEDGER!$G:$G) | K37: =I37-J37 | L37: =J37+CD37 | M37: =I37-L37 | R37: =SUM(N37:Q37) | W37: =SUM(S37:V37) | AC37: =SUM(X37:AB37) | AD37: =R37+W37+AC37 | AI37: =SUM(AE37:AH37) | AN37: =SUM(AJ37:AM37) | AT37: =SUM(AO37:AS37) | AU37: =AI37+AN37+AT37 | AZ37: =SUM(AV37:AY37) | BF37: =SUM(BA37:BE37) | BK37: =SUM(BG37:BJ37) | BL37: =AZ37+BF37+BK37 | BQ37: =SUM(BM37:BP37) | BR37: 100000 | BW37: =SUM(BR37:BV37) | CB37: =SUM(BX37:CA37) | CC37: =BQ37+BW37+CB37 | CD37: =AD37+AU37+BL37+CC37
A38: Approved | B38: 5.7 | C38: Legal Expenses - Land Use SINAC | D38: Eduardo | E38: Concessions | F38: SETENA Regional Review | G38: 50000 | H38: 0 | I38: =G38+H38 | J38: =SUMIF(LEDGER!$A:$A,$B38,LEDGER!$G:$G) | K38: =I38-J38 | L38: =J38+CD38 | M38: =I38-L38 | R38: =SUM(N38:Q38) | W38: =SUM(S38:V38) | AC38: =SUM(X38:AB38) | AD38: =R38+W38+AC38 | AI38: =SUM(AE38:AH38) | AM38: 20000 | AN38: =SUM(AJ38:AM38) | AT38: =SUM(AO38:AS38) | AU38: =AI38+AN38+AT38 | AY38: 20000 | AZ38: =SUM(AV38:AY38) | BF38: =SUM(BA38:BE38) | BJ38: 10000 | BK38: =SUM(BG38:BJ38) | BL38: =AZ38+BF38+BK38 | BQ38: =SUM(BM38:BP38) | BW38: =SUM(BR38:BV38) | CB38: =SUM(BX38:CA38) | CC38: =BQ38+BW38+CB38 | CD38: =AD38+AU38+BL38+CC38
A39: In process | B39: 5.8 | C39: Legal Expenses - Land Use Concessions (ALTA BATALLA)} | D39: Roberto | E39: Concessions | F39: SETENA Regional Review | G39: 14500 | H39: 0 | I39: =G39+H39 | J39: =SUMIF(LEDGER!$A:$A,$B39,LEDGER!$G:$G) | K39: =I39-J39 | L39: =J39+CD39 | M39: =I39-L39 | R39: =SUM(N39:Q39) | W39: =SUM(S39:V39) | AC39: =SUM(X39:AB39) | AD39: =R39+W39+AC39 | AI39: =SUM(AE39:AH39) | AN39: =SUM(AJ39:AM39) | AO39: 7250 | AT39: =SUM(AO39:AS39) | AU39: =AI39+AN39+AT39 | AZ39: =SUM(AV39:AY39) | BF39: =SUM(BA39:BE39) | BK39: =SUM(BG39:BJ39) | BL39: =AZ39+BF39+BK39 | BM39: 7250 | BQ39: =SUM(BM39:BP39) | BW39: =SUM(BR39:BV39) | CB39: =SUM(BX39:CA39) | CC39: =BQ39+BW39+CB39 | CD39: =AD39+AU39+BL39+CC39
A40: Approved | B40: 8.3 | C40: Finalize Creation of Concessions | D40: Blake | E40: Concessions | G40: 42375 | H40: 0 | I40: =G40+H40 | J40: =SUMIF(LEDGER!$A:$A,$B40,LEDGER!$G:$G) | K40: =I40-J40 | L40: =J40+CD40 | M40: =I40-L40 | R40: =SUM(N40:Q40) | W40: =SUM(S40:V40) | AC40: =SUM(X40:AB40) | AD40: =R40+W40+AC40 | AI40: =SUM(AE40:AH40) | AN40: =SUM(AJ40:AM40) | AT40: =SUM(AO40:AS40) | AU40: =AI40+AN40+AT40 | AZ40: =SUM(AV40:AY40) | BF40: =SUM(BA40:BE40) | BK40: =SUM(BG40:BJ40) | BL40: =AZ40+BF40+BK40 | BQ40: =SUM(BM40:BP40) | BW40: =SUM(BR40:BV40) | CA40: 42375 | CB40: =SUM(BX40:CA40) | CC40: =BQ40+BW40+CB40 | CD40: =AD40+AU40+BL40+CC40
C41: TOTAL Concessions | G41: =G32+G33+G34+G35+G36+G37+G38+G39+G40 | H41: =H32+H33+H34+H35+H36+H37+H38+H39+H40 | I41: =I32+I33+I34+I35+I36+I37+I38+I39+I40 | J41: =J32+J33+J34+J35+J36+J37+J38+J39+J40 | K41: =K32+K33+K34+K35+K36+K37+K38+K39+K40 | L41: =L32+L33+L34+L35+L36+L37+L38+L39+L40 | M41: =M32+M33+M34+M35+M36+M37+M38+M39+M40 | R41: =R32+R33+R34+R35+R36+R37+R38+R39+R40 | W41: =W32+W33+W34+W35+W36+W37+W38+W39+W40 | AC41: =AC32+AC33+AC34+AC35+AC36+AC37+AC38+AC39+AC40 | AD41: =AD32+AD33+AD34+AD35+AD36+AD37+AD38+AD39+AD40 | AI41: =AI32+AI33+AI34+AI35+AI36+AI37+AI38+AI39+AI40 | AN41: =AN32+AN33+AN34+AN35+AN36+AN37+AN38+AN39+AN40 | AT41: =AT32+AT33+AT34+AT35+AT36+AT37+AT38+AT39+AT40 | AU41: =AU32+AU33+AU34+AU35+AU36+AU37+AU38+AU39+AU40 | AZ41: =AZ32+AZ33+AZ34+AZ35+AZ36+AZ37+AZ38+AZ39+AZ40 | BF41: =BF32+BF33+BF34+BF35+BF36+BF37+BF38+BF39+BF40 | BK41: =BK32+BK33+BK34+BK35+BK36+BK37+BK38+BK39+BK40 | BL41: =BL32+BL33+BL34+BL35+BL36+BL37+BL38+BL39+BL40 | BQ41: =BQ32+BQ33+BQ34+BQ35+BQ36+BQ37+BQ38+BQ39+BQ40 | BW41: =BW32+BW33+BW34+BW35+BW36+BW37+BW38+BW39+BW40 | CB41: =CB32+CB33+CB34+CB35+CB36+CB37+CB38+CB39+CB40 | CC41: =CC32+CC33+CC34+CC35+CC36+CC37+CC38+CC39+CC40 | CD41: =CD32+CD33+CD34+CD35+CD36+CD37+CD38+CD39+CD40
A42: OVERHEAD
A43: Approved | B43: 0.1 | C43: Property Interest | D43: Partnership | E43: Overhead | F43: Phase 2 | G43: 787500 | H43: 0 | I43: =G43+H43 | J43: =SUMIF(LEDGER!$A:$A,$B43,LEDGER!$G:$G) | K43: =I43-J43 | L43: =J43+CD43 | M43: =I43-L43 | R43: =SUM(N43:Q43) | W43: =SUM(S43:V43) | AC43: =SUM(X43:AB43) | AD43: =R43+W43+AC43 | AI43: =SUM(AE43:AH43) | AN43: =SUM(AJ43:AM43) | AT43: =SUM(AO43:AS43) | AU43: =AI43+AN43+AT43 | AZ43: =SUM(AV43:AY43) | BF43: =SUM(BA43:BE43) | BJ43: 337500 | BK43: =SUM(BG43:BJ43) | BL43: =AZ43+BF43+BK43 | BQ43: =SUM(BM43:BP43) | BW43: =SUM(BR43:BV43) | CB43: =SUM(BX43:CA43) | CC43: =BQ43+BW43+CB43 | CD43: =AD43+AU43+BL43+CC43
A44: Approved | B44: 0.1.1 | C44: Insurance | D44: Partnership | E44: Overhead | F44: Phase 2 | G44: 20000 | H44: 0 | I44: =G44+H44 | J44: =SUMIF(LEDGER!$A:$A,$B44,LEDGER!$G:$G) | K44: =I44-J44 | L44: =J44+CD44 | M44: =I44-L44 | R44: =SUM(N44:Q44) | W44: =SUM(S44:V44) | AC44: =SUM(X44:AB44) | AD44: =R44+W44+AC44 | AI44: =SUM(AE44:AH44) | AN44: =SUM(AJ44:AM44) | AT44: =SUM(AO44:AS44) | AU44: =AI44+AN44+AT44 | AZ44: =SUM(AV44:AY44) | BF44: =SUM(BA44:BE44) | BJ44: 20000 | BK44: =SUM(BG44:BJ44) | BL44: =AZ44+BF44+BK44 | BQ44: =SUM(BM44:BP44) | BW44: =SUM(BR44:BV44) | CB44: =SUM(BX44:CA44) | CC44: =BQ44+BW44+CB44 | CD44: =AD44+AU44+BL44+CC44
A45: Attention | B45: 0.1.2 | C45: Titled Property Annual Taxes | D45: Partnership | E45: Overhead | F45: Phase 2 | G45: 75000 | H45: 0 | I45: =G45+H45 | J45: =SUMIF(LEDGER!$A:$A,$B45,LEDGER!$G:$G) | K45: =I45-J45 | L45: =J45+CD45 | M45: =I45-L45 | R45: =SUM(N45:Q45) | V45: 37500 | W45: =SUM(S45:V45) | AC45: =SUM(X45:AB45) | AD45: =R45+W45+AC45 | AI45: =SUM(AE45:AH45) | AN45: =SUM(AJ45:AM45) | AT45: =SUM(AO45:AS45) | AU45: =AI45+AN45+AT45 | AZ45: =SUM(AV45:AY45) | BF45: =SUM(BA45:BE45) | BJ45: 37500 | BK45: =SUM(BG45:BJ45) | BL45: =AZ45+BF45+BK45 | BQ45: =SUM(BM45:BP45) | BW45: =SUM(BR45:BV45) | CB45: =SUM(BX45:CA45) | CC45: =BQ45+BW45+CB45 | CD45: =AD45+AU45+BL45+CC45
A46: Attention | B46: 0.1.3 | C46: Holding Corporation Taxes | D46: Partnership | E46: Overhead | F46: Phase 2 | G46: 12600 | H46: 0 | I46: =G46+H46 | J46: =SUMIF(LEDGER!$A:$A,$B46,LEDGER!$G:$G) | K46: =I46-J46 | L46: =J46+CD46 | M46: =I46-L46 | R46: =SUM(N46:Q46) | V46: 6300 | W46: =SUM(S46:V46) | AC46: =SUM(X46:AB46) | AD46: =R46+W46+AC46 | AI46: =SUM(AE46:AH46) | AN46: =SUM(AJ46:AM46) | AT46: =SUM(AO46:AS46) | AU46: =AI46+AN46+AT46 | AZ46: =SUM(AV46:AY46) | BF46: =SUM(BA46:BE46) | BJ46: 6300 | BK46: =SUM(BG46:BJ46) | BL46: =AZ46+BF46+BK46 | BQ46: =SUM(BM46:BP46) | BW46: =SUM(BR46:BV46) | CB46: =SUM(BX46:CA46) | CC46: =BQ46+BW46+CB46 | CD46: =AD46+AU46+BL46+CC46
A47: Approved | B47: 0.2 | C47: Concession/Land Use Leases | D47: Partnership | E47: Overhead | F47: Phase 2 | G47: 87000 | H47: 0 | I47: =G47+H47 | J47: =SUMIF(LEDGER!$A:$A,$B47,LEDGER!$G:$G) | K47: =I47-J47 | L47: =J47+CD47 | M47: =I47-L47 | R47: =SUM(N47:Q47) | W47: =SUM(S47:V47) | AC47: =SUM(X47:AB47) | AD47: =R47+W47+AC47 | AI47: =SUM(AE47:AH47) | AM47: 4492.5 | AN47: =SUM(AJ47:AM47) | AT47: =SUM(AO47:AS47) | AU47: =AI47+AN47+AT47 | AZ47: =SUM(AV47:AY47) | BF47: =SUM(BA47:BE47) | BK47: =SUM(BG47:BJ47) | BL47: =AZ47+BF47+BK47 | BQ47: =SUM(BM47:BP47) | BW47: =SUM(BR47:BV47) | CB47: =SUM(BX47:CA47) | CC47: =BQ47+BW47+CB47 | CD47: =AD47+AU47+BL47+CC47
A48: Attention | B48: 0.3 | C48: Escrow and Legal Fees | D48: Sergio Amador | E48: Overhead | F48: Phase 2 | G48: 40000 | H48: 10795.05 | I48: =G48+H48 | J48: =SUMIF(LEDGER!$A:$A,$B48,LEDGER!$G:$G) | K48: =I48-J48 | L48: =J48+CD48 | M48: =I48-L48 | R48: =SUM(N48:Q48) | W48: =SUM(S48:V48) | AC48: =SUM(X48:AB48) | AD48: =R48+W48+AC48 | AI48: =SUM(AE48:AH48) | AN48: =SUM(AJ48:AM48) | AT48: =SUM(AO48:AS48) | AU48: =AI48+AN48+AT48 | AZ48: =SUM(AV48:AY48) | BF48: =SUM(BA48:BE48) | BK48: =SUM(BG48:BJ48) | BL48: =AZ48+BF48+BK48 | BQ48: =SUM(BM48:BP48) | BW48: =SUM(BR48:BV48) | CB48: =SUM(BX48:CA48) | CC48: =BQ48+BW48+CB48 | CD48: =AD48+AU48+BL48+CC48
A49: Attention | B49: 0.3.1 | C49: Corporation Management | D49: Sergio Amador | E49: Overhead | F49: Phase 2 | G49: 15000 | H49: 4686.1 | I49: =G49+H49 | J49: =SUMIF(LEDGER!$A:$A,$B49,LEDGER!$G:$G) | K49: =I49-J49 | L49: =J49+CD49 | M49: =I49-L49 | R49: =SUM(N49:Q49) | W49: =SUM(S49:V49) | AC49: =SUM(X49:AB49) | AD49: =R49+W49+AC49 | AI49: =SUM(AE49:AH49) | AN49: =SUM(AJ49:AM49) | AT49: =SUM(AO49:AS49) | AU49: =AI49+AN49+AT49 | AZ49: =SUM(AV49:AY49) | BF49: =SUM(BA49:BE49) | BK49: =SUM(BG49:BJ49) | BL49: =AZ49+BF49+BK49 | BQ49: =SUM(BM49:BP49) | BW49: =SUM(BR49:BV49) | CB49: =SUM(BX49:CA49) | CC49: =BQ49+BW49+CB49 | CD49: =AD49+AU49+BL49+CC49
A50: Attention | B50: 0.4 | C50: Admin Fee Budget + Financial Controller 25% Salary | D50: Partnership | E50: Overhead | F50: Phase 2 | G50: 86250 | H50: 7500 | I50: =G50+H50 | J50: =SUMIF(LEDGER!$A:$A,$B50,LEDGER!$G:$G) | K50: =I50-J50 | L50: =J50+CD50 | M50: =I50-L50 | Q50: 3750 | R50: =SUM(N50:Q50) | V50: 3750 | W50: =SUM(S50:V50) | AA50: 3750 | AC50: =SUM(X50:AB50) | AD50: =R50+W50+AC50 | AH50: 3750 | AI50: =SUM(AE50:AH50) | AM50: 3750 | AN50: =SUM(AJ50:AM50) | AR50: 3750 | AT50: =SUM(AO50:AS50) | AU50: =AI50+AN50+AT50 | AY50: 3750 | AZ50: =SUM(AV50:AY50) | BD50: 3750 | BF50: =SUM(BA50:BE50) | BJ50: 3250 | BK50: =SUM(BG50:BJ50) | BL50: =AZ50+BF50+BK50 | BP50: 3750 | BQ50: =SUM(BM50:BP50) | BU50: 3750 | BW50: =SUM(BR50:BV50) | CA50: 3750 | CB50: =SUM(BX50:CA50) | CC50: =BQ50+BW50+CB50 | CD50: =AD50+AU50+BL50+CC50
A51: Approved | B51: 0.5 | C51: Travel Expenses / Ownership | D51: Partnership | E51: Overhead | F51: Phase 2 | G51: 24000 | H51: 19641.38 | I51: =G51+H51 | J51: =SUMIF(LEDGER!$A:$A,$B51,LEDGER!$G:$G) | K51: =I51-J51 | L51: =J51+CD51 | M51: =I51-L51 | R51: =SUM(N51:Q51) | W51: =SUM(S51:V51) | AC51: =SUM(X51:AB51) | AD51: =R51+W51+AC51 | AI51: =SUM(AE51:AH51) | AN51: =SUM(AJ51:AM51) | AT51: =SUM(AO51:AS51) | AU51: =AI51+AN51+AT51 | AZ51: =SUM(AV51:AY51) | BF51: =SUM(BA51:BE51) | BK51: =SUM(BG51:BJ51) | BL51: =AZ51+BF51+BK51 | BQ51: =SUM(BM51:BP51) | BW51: =SUM(BR51:BV51) | CB51: =SUM(BX51:CA51) | CC51: =BQ51+BW51+CB51 | CD51: =AD51+AU51+BL51+CC51
A52: Attention | B52: 0.6.1 | C52: Farm Manager | D52: Alexis | E52: Overhead | F52: Phase 2 | G52: 23000 | H52: 19334.4 | I52: =G52+H52 | J52: =SUMIF(LEDGER!$A:$A,$B52,LEDGER!$G:$G) | K52: =I52-J52 | L52: =J52+CD52 | M52: =I52-L52 | Q52: 1824.71 | R52: =SUM(N52:Q52) | V52: 1824.71 | W52: =SUM(S52:V52) | AA52: 1824.71 | AC52: =SUM(X52:AB52) | AD52: =R52+W52+AC52 | AH52: 1824.71 | AI52: =SUM(AE52:AH52) | AM52: 1824.71 | AN52: =SUM(AJ52:AM52) | AR52: 1824.71 | AT52: =SUM(AO52:AS52) | AU52: =AI52+AN52+AT52 | AY52: 1824.71 | AZ52: =SUM(AV52:AY52) | BD52: 1824.71 | BF52: =SUM(BA52:BE52) | BJ52: 1824.71 | BK52: =SUM(BG52:BJ52) | BL52: =AZ52+BF52+BK52 | BP52: 1824.71 | BQ52: =SUM(BM52:BP52) | BU52: 1824.71 | BW52: =SUM(BR52:BV52) | CA52: 1824.71 | CB52: =SUM(BX52:CA52) | CC52: =BQ52+BW52+CB52 | CD52: =AD52+AU52+BL52+CC52
A53: Attention | B53: 0.6.2 | C53: Farm Worker | D53: TBD | E53: Overhead | F53: Phase 2 | G53: 13800 | H53: 2569.41 | I53: =G53+H53 | J53: =SUMIF(LEDGER!$A:$A,$B53,LEDGER!$G:$G) | K53: =I53-J53 | L53: =J53+CD53 | M53: =I53-L53 | Q53: 1000 | R53: =SUM(N53:Q53) | V53: 1000 | W53: =SUM(S53:V53) | AA53: 1000 | AC53: =SUM(X53:AB53) | AD53: =R53+W53+AC53 | AH53: 1000 | AI53: =SUM(AE53:AH53) | AM53: 1000 | AN53: =SUM(AJ53:AM53) | AR53: 1000 | AT53: =SUM(AO53:AS53) | AU53: =AI53+AN53+AT53 | AY53: 1000 | AZ53: =SUM(AV53:AY53) | BD53: 600 | BF53: =SUM(BA53:BE53) | BJ53: 1000 | BK53: =SUM(BG53:BJ53) | BL53: =AZ53+BF53+BK53 | BP53: 1000 | BQ53: =SUM(BM53:BP53) | BU53: 1000 | BW53: =SUM(BR53:BV53) | CA53: 1000 | CB53: =SUM(BX53:CA53) | CC53: =BQ53+BW53+CB53 | CD53: =AD53+AU53+BL53+CC53
A54: Attention | B54: 0.6.3 | C54: CCSS Employee Benefits | E54: Overhead | F54: Phase 2 | G54: 18400 | H54: 0 | I54: =G54+H54 | J54: =SUMIF(LEDGER!$A:$A,$B54,LEDGER!$G:$G) | K54: =I54-J54 | L54: =J54+CD54 | M54: =I54-L54 | Q54: 1392.36 | R54: =SUM(N54:Q54) | V54: 1412.36 | W54: =SUM(S54:V54) | AA54: 1412.36 | AC54: =SUM(X54:AB54) | AD54: =R54+W54+AC54 | AH54: 1412.36 | AI54: =SUM(AE54:AH54) | AM54: 1412.36 | AN54: =SUM(AJ54:AM54) | AR54: 1412.36 | AT54: =SUM(AO54:AS54) | AU54: =AI54+AN54+AT54 | AY54: 1412.36 | AZ54: =SUM(AV54:AY54) | BD54: 1212.36 | BF54: =SUM(BA54:BE54) | BJ54: 1412.36 | BK54: =SUM(BG54:BJ54) | BL54: =AZ54+BF54+BK54 | BP54: 1412.36 | BQ54: =SUM(BM54:BP54) | BU54: 1412.36 | BW54: =SUM(BR54:BV54) | BZ54: 1671.74 | CA54: 1412.36 | CB54: =SUM(BX54:CA54) | CC54: =BQ54+BW54+CB54 | CD54: =AD54+AU54+BL54+CC54
A55: Approved | B55: 0.6.4 | C55: Main. Equip. / Expendables / Truck / Mula | D55: Blake | E55: Overhead | F55: Phase 2 | G55: 62500 | H55: 0 | I55: =G55+H55 | J55: =SUMIF(LEDGER!$A:$A,$B55,LEDGER!$G:$G) | K55: =I55-J55 | L55: =J55+CD55 | M55: =I55-L55 | R55: =SUM(N55:Q55) | W55: =SUM(S55:V55) | AC55: =SUM(X55:AB55) | AD55: =R55+W55+AC55 | AI55: =SUM(AE55:AH55) | AJ55: 2500 | AK55: 29998 | AN55: =SUM(AJ55:AM55) | AR55: 2500 | AT55: =SUM(AO55:AS55) | AU55: =AI55+AN55+AT55 | AZ55: =SUM(AV55:AY55) | BF55: =SUM(BA55:BE55) | BJ55: 2500 | BK55: =SUM(BG55:BJ55) | BL55: =AZ55+BF55+BK55 | BQ55: =SUM(BM55:BP55) | BW55: =SUM(BR55:BV55) | CB55: =SUM(BX55:CA55) | CC55: =BQ55+BW55+CB55 | CD55: =AD55+AU55+BL55+CC55
A56: Approved | B56: 0.6.5 | C56: Procore (If we want to implement is system) | D56: Blake | E56: Overhead | F56: Phase 2 | G56: 21000 | H56: 0 | I56: =G56+H56 | J56: =SUMIF(LEDGER!$A:$A,$B56,LEDGER!$G:$G) | K56: =I56-J56 | L56: =J56+CD56 | M56: =I56-L56 | R56: =SUM(N56:Q56) | W56: =SUM(S56:V56) | AC56: =SUM(X56:AB56) | AD56: =R56+W56+AC56 | AI56: =SUM(AE56:AH56) | AK56: 13000 | AN56: =SUM(AJ56:AM56) | AT56: =SUM(AO56:AS56) | AU56: =AI56+AN56+AT56 | AZ56: =SUM(AV56:AY56) | BF56: =SUM(BA56:BE56) | BK56: =SUM(BG56:BJ56) | BL56: =AZ56+BF56+BK56 | BQ56: =SUM(BM56:BP56) | BW56: =SUM(BR56:BV56) | CA56: 8000 | CB56: =SUM(BX56:CA56) | CC56: =BQ56+BW56+CB56 | CD56: =AD56+AU56+BL56+CC56
A57: Attention | B57: 0.7 | C57: Development Director | D57: Blake | E57: Overhead | F57: Phase 2 | G57: 324875 | H57: 68170 | I57: =G57+H57 | J57: =SUMIF(LEDGER!$A:$A,$B57,LEDGER!$G:$G) | K57: =I57-J57 | L57: =J57+CD57 | M57: =I57-L57 | Q57: 14125 | R57: =SUM(N57:Q57) | V57: 14125 | W57: =SUM(S57:V57) | AA57: 14125 | AC57: =SUM(X57:AB57) | AD57: =R57+W57+AC57 | AH57: 14125 | AI57: =SUM(AE57:AH57) | AM57: 14125 | AN57: =SUM(AJ57:AM57) | AR57: 14125 | AT57: =SUM(AO57:AS57) | AU57: =AI57+AN57+AT57 | AY57: 14125 | AZ57: =SUM(AV57:AY57) | BD57: 14125 | BF57: =SUM(BA57:BE57) | BJ57: 14125 | BK57: =SUM(BG57:BJ57) | BL57: =AZ57+BF57+BK57 | BP57: 14125 | BQ57: =SUM(BM57:BP57) | BU57: 14125 | BW57: =SUM(BR57:BV57) | CA57: 14125 | CB57: =SUM(BX57:CA57) | CC57: =BQ57+BW57+CB57 | CD57: =AD57+AU57+BL57+CC57
A58: In process | B58: 0.8 | C58: Road Repairs | D58: FyF | E58: Overhead | F58: Phase 2 | G58: 30000 | H58: 0 | I58: =G58+H58 | J58: =SUMIF(LEDGER!$A:$A,$B58,LEDGER!$G:$G) | K58: =I58-J58 | L58: =J58+CD58 | M58: =I58-L58 | R58: =SUM(N58:Q58) | W58: =SUM(S58:V58) | AC58: =SUM(X58:AB58) | AD58: =R58+W58+AC58 | AE58: 30000 | AI58: =SUM(AE58:AH58) | AN58: =SUM(AJ58:AM58) | AT58: =SUM(AO58:AS58) | AU58: =AI58+AN58+AT58 | AZ58: =SUM(AV58:AY58) | BF58: =SUM(BA58:BE58) | BK58: =SUM(BG58:BJ58) | BL58: =AZ58+BF58+BK58 | BQ58: =SUM(BM58:BP58) | BW58: =SUM(BR58:BV58) | CB58: =SUM(BX58:CA58) | CC58: =BQ58+BW58+CB58 | CD58: =AD58+AU58+BL58+CC58
A59: Approved | B59: 0.9 | C59: Fallen Trees / Cutting Grass | D59: Alexis/Gustavo | E59: Overhead | F59: Phase 2 | G59: 16000 | H59: 24000 | I59: =G59+H59 | J59: =SUMIF(LEDGER!$A:$A,$B59,LEDGER!$G:$G) | K59: =I59-J59 | L59: =J59+CD59 | M59: =I59-L59 | R59: =SUM(N59:Q59) | V59: 2000 | W59: =SUM(S59:V59) | AC59: =SUM(X59:AB59) | AD59: =R59+W59+AC59 | AI59: =SUM(AE59:AH59) | AM59: 2000 | AN59: =SUM(AJ59:AM59) | AT59: =SUM(AO59:AS59) | AU59: =AI59+AN59+AT59 | AZ59: =SUM(AV59:AY59) | BD59: 2000 | BF59: =SUM(BA59:BE59) | BK59: =SUM(BG59:BJ59) | BL59: =AZ59+BF59+BK59 | BM59: 31840.2 | BQ59: =SUM(BM59:BP59) | BW59: =SUM(BR59:BV59) | CB59: =SUM(BX59:CA59) | CC59: =BQ59+BW59+CB59 | CD59: =AD59+AU59+BL59+CC59
A60: In process | B60: 0.911 | C60: Property Gates | D60: Blake | E60: Overhead | F60: Phase 2 | G60: 6000 | H60: 1400 | I60: =G60+H60 | J60: =SUMIF(LEDGER!$A:$A,$B60,LEDGER!$G:$G) | K60: =I60-J60 | L60: =J60+CD60 | M60: =I60-L60 | R60: =SUM(N60:Q60) | W60: =SUM(S60:V60) | AC60: =SUM(X60:AB60) | AD60: =R60+W60+AC60 | AI60: =SUM(AE60:AH60) | AN60: =SUM(AJ60:AM60) | AT60: =SUM(AO60:AS60) | AU60: =AI60+AN60+AT60 | AZ60: =SUM(AV60:AY60) | BF60: =SUM(BA60:BE60) | BK60: =SUM(BG60:BJ60) | BL60: =AZ60+BF60+BK60 | BQ60: =SUM(BM60:BP60) | BW60: =SUM(BR60:BV60) | CB60: =SUM(BX60:CA60) | CC60: =BQ60+BW60+CB60 | CD60: =AD60+AU60+BL60+CC60
A61: Attention | B61: 1.1 | C61: Gravel Existing Roads | D61: FyF | E61: Overhead | F61: Phase 3 | G61: 80000 | H61: 0 | I61: =G61+H61 | J61: =SUMIF(LEDGER!$A:$A,$B61,LEDGER!$G:$G) | K61: =I61-J61 | L61: =J61+CD61 | M61: =I61-L61 | R61: =SUM(N61:Q61) | W61: =SUM(S61:V61) | AC61: =SUM(X61:AB61) | AD61: =R61+W61+AC61 | AI61: =SUM(AE61:AH61) | AM61: 40000 | AN61: =SUM(AJ61:AM61) | AR61: 40000 | AT61: =SUM(AO61:AS61) | AU61: =AI61+AN61+AT61 | AZ61: =SUM(AV61:AY61) | BF61: =SUM(BA61:BE61) | BK61: =SUM(BG61:BJ61) | BL61: =AZ61+BF61+BK61 | BQ61: =SUM(BM61:BP61) | BW61: =SUM(BR61:BV61) | CB61: =SUM(BX61:CA61) | CC61: =BQ61+BW61+CB61 | CD61: =AD61+AU61+BL61+CC61
A62: Approved | B62: 1.2 | C62: Opening Views | D62: Tree Man Co. | E62: Overhead | F62: Phase 3 | G62: 52800 | H62: 0 | I62: =G62+H62 | J62: =SUMIF(LEDGER!$A:$A,$B62,LEDGER!$G:$G) | K62: =I62-J62 | L62: =J62+CD62 | M62: =I62-L62 | R62: =SUM(N62:Q62) | W62: =SUM(S62:V62) | AC62: =SUM(X62:AB62) | AD62: =R62+W62+AC62 | AI62: =SUM(AE62:AH62) | AM62: 28380 | AN62: =SUM(AJ62:AM62) | AT62: =SUM(AO62:AS62) | AU62: =AI62+AN62+AT62 | AZ62: =SUM(AV62:AY62) | BF62: =SUM(BA62:BE62) | BG62: 4400 | BH62: 4400 | BI62: 4400 | BJ62: 4400 | BK62: =SUM(BG62:BJ62) | BL62: =AZ62+BF62+BK62 | BQ62: =SUM(BM62:BP62) | BW62: =SUM(BR62:BV62) | CB62: =SUM(BX62:CA62) | CC62: =BQ62+BW62+CB62 | CD62: =AD62+AU62+BL62+CC62
A63: Attention | B63: 1.3 | C63: Opening Paths to Important Areas | D63: Alexis | E63: Overhead | F63: Phase 3 | G63: 6480 | H63: 0 | I63: =G63+H63 | J63: =SUMIF(LEDGER!$A:$A,$B63,LEDGER!$G:$G) | K63: =I63-J63 | L63: =J63+CD63 | M63: =I63-L63 | R63: =SUM(N63:Q63) | W63: =SUM(S63:V63) | AC63: =SUM(X63:AB63) | AD63: =R63+W63+AC63 | AI63: =SUM(AE63:AH63) | AN63: =SUM(AJ63:AM63) | AT63: =SUM(AO63:AS63) | AU63: =AI63+AN63+AT63 | AZ63: =SUM(AV63:AY63) | BF63: =SUM(BA63:BE63) | BK63: =SUM(BG63:BJ63) | BL63: =AZ63+BF63+BK63 | BQ63: =SUM(BM63:BP63) | BW63: =SUM(BR63:BV63) | CB63: =SUM(BX63:CA63) | CC63: =BQ63+BW63+CB63 | CD63: =AD63+AU63+BL63+CC63
A64: Attention | B64: 1.4 | C64: Water System | D64: Blake | E64: Overhead | F64: Phase 3 | G64: 155000 | H64: 50314.4 | I64: =G64+H64 | J64: =SUMIF(LEDGER!$A:$A,$B64,LEDGER!$G:$G) | K64: =I64-J64 | L64: =J64+CD64 | M64: =I64-L64 | R64: =SUM(N64:Q64) | W64: =SUM(S64:V64) | AC64: =SUM(X64:AB64) | AD64: =R64+W64+AC64 | AI64: =SUM(AE64:AH64) | AN64: =SUM(AJ64:AM64) | AT64: =SUM(AO64:AS64) | AU64: =AI64+AN64+AT64 | AZ64: =SUM(AV64:AY64) | BF64: =SUM(BA64:BE64) | BK64: =SUM(BG64:BJ64) | BL64: =AZ64+BF64+BK64 | BQ64: =SUM(BM64:BP64) | BW64: =SUM(BR64:BV64) | CB64: =SUM(BX64:CA64) | CC64: =BQ64+BW64+CB64 | CD64: =AD64+AU64+BL64+CC64
A65: Approved | B65: 6.1 | C65: Trim Trees to See View | D65: Tree Man Co. | E65: Overhead | F65: PROPERTY | G65: 7500 | H65: 0 | I65: =G65+H65 | J65: =SUMIF(LEDGER!$A:$A,$B65,LEDGER!$G:$G) | K65: =I65-J65 | L65: =J65+CD65 | M65: =I65-L65 | R65: =SUM(N65:Q65) | W65: =SUM(S65:V65) | AC65: =SUM(X65:AB65) | AD65: =R65+W65+AC65 | AE65: 7500 | AI65: =SUM(AE65:AH65) | AN65: =SUM(AJ65:AM65) | AT65: =SUM(AO65:AS65) | AU65: =AI65+AN65+AT65 | AZ65: =SUM(AV65:AY65) | BF65: =SUM(BA65:BE65) | BK65: =SUM(BG65:BJ65) | BL65: =AZ65+BF65+BK65 | BQ65: =SUM(BM65:BP65) | BW65: =SUM(BR65:BV65) | CB65: =SUM(BX65:CA65) | CC65: =BQ65+BW65+CB65 | CD65: =AD65+AU65+BL65+CC65
A66: Approved | B66: 6.2 | C66: Survey Water Easement and Register | D66: Marvin | E66: Overhead | F66: PROPERTY | G66: 7500 | H66: 5450 | I66: =G66+H66 | J66: =SUMIF(LEDGER!$A:$A,$B66,LEDGER!$G:$G) | K66: =I66-J66 | L66: =J66+CD66 | M66: =I66-L66 | R66: =SUM(N66:Q66) | W66: =SUM(S66:V66) | AC66: =SUM(X66:AB66) | AD66: =R66+W66+AC66 | AI66: =SUM(AE66:AH66) | AN66: =SUM(AJ66:AM66) | AT66: =SUM(AO66:AS66) | AU66: =AI66+AN66+AT66 | AV66: 2500 | AZ66: =SUM(AV66:AY66) | BF66: =SUM(BA66:BE66) | BK66: =SUM(BG66:BJ66) | BL66: =AZ66+BF66+BK66 | BQ66: =SUM(BM66:BP66) | BW66: =SUM(BR66:BV66) | CB66: =SUM(BX66:CA66) | CC66: =BQ66+BW66+CB66 | CD66: =AD66+AU66+BL66+CC66
A67: Approved | B67: 6.3 | C67: Cut Driveway and Building Pad + Gravel + Culverts | D67: Sibaja | E67: Overhead | F67: PROPERTY | G67: 20000 | H67: 20000 | I67: =G67+H67 | J67: =SUMIF(LEDGER!$A:$A,$B67,LEDGER!$G:$G) | K67: =I67-J67 | L67: =J67+CD67 | M67: =I67-L67 | R67: =SUM(N67:Q67) | W67: =SUM(S67:V67) | AC67: =SUM(X67:AB67) | AD67: =R67+W67+AC67 | AI67: =SUM(AE67:AH67) | AN67: =SUM(AJ67:AM67) | AT67: =SUM(AO67:AS67) | AU67: =AI67+AN67+AT67 | AZ67: =SUM(AV67:AY67) | BF67: =SUM(BA67:BE67) | BK67: =SUM(BG67:BJ67) | BL67: =AZ67+BF67+BK67 | BM67: 22416.85 | BQ67: =SUM(BM67:BP67) | BW67: =SUM(BR67:BV67) | CB67: =SUM(BX67:CA67) | CC67: =BQ67+BW67+CB67 | CD67: =AD67+AU67+BL67+CC67
A68: Approved | B68: 6.4 | C68: Closing Costs | D68: Karol | E68: Overhead | F68: PROPERTY | G68: 48000 | H68: 0 | I68: =G68+H68 | J68: =SUMIF(LEDGER!$A:$A,$B68,LEDGER!$G:$G) | K68: =I68-J68 | L68: =J68+CD68 | M68: =I68-L68 | R68: =SUM(N68:Q68) | W68: =SUM(S68:V68) | X68: 48000 | AC68: =SUM(X68:AB68) | AD68: =R68+W68+AC68 | AI68: =SUM(AE68:AH68) | AN68: =SUM(AJ68:AM68) | AT68: =SUM(AO68:AS68) | AU68: =AI68+AN68+AT68 | AZ68: =SUM(AV68:AY68) | BF68: =SUM(BA68:BE68) | BK68: =SUM(BG68:BJ68) | BL68: =AZ68+BF68+BK68 | BQ68: =SUM(BM68:BP68) | BW68: =SUM(BR68:BV68) | CB68: =SUM(BX68:CA68) | CC68: =BQ68+BW68+CB68 | CD68: =AD68+AU68+BL68+CC68
B69: 6 | C69: Property Sale | D69: Karol | E69: Overhead | F69: PROPERTY | G69: -480000 | H69: 0 | I69: =G69+H69 | J69: =SUMIF(LEDGER!$A:$A,$B69,LEDGER!$G:$G) | K69: =I69-J69 | L69: =J69+CD69 | M69: =I69-L69 | R69: =SUM(N69:Q69) | W69: =SUM(S69:V69) | X69: -480000 | AC69: =SUM(X69:AB69) | AD69: =R69+W69+AC69 | AI69: =SUM(AE69:AH69) | AN69: =SUM(AJ69:AM69) | AT69: =SUM(AO69:AS69) | AU69: =AI69+AN69+AT69 | AZ69: =SUM(AV69:AY69) | BF69: =SUM(BA69:BE69) | BK69: =SUM(BG69:BJ69) | BL69: =AZ69+BF69+BK69 | BQ69: =SUM(BM69:BP69) | BW69: =SUM(BR69:BV69) | CB69: =SUM(BX69:CA69) | CC69: =BQ69+BW69+CB69 | CD69: =AD69+AU69+BL69+CC69
C70: TOTAL Overhead | G70: =G43+G44+G45+G46+G47+G48+G49+G50+G51+G52+G53+G54+G55+G56+G57+G58+G59+G60+G61+G62+G63+G64+G65+G66+G67+G68+G69 | H70: =H43+H44+H45+H46+H47+H48+H49+H50+H51+H52+H53+H54+H55+H56+H57+H58+H59+H60+H61+H62+H63+H64+H65+H66+H67+H68+H69 | I70: =I43+I44+I45+I46+I47+I48+I49+I50+I51+I52+I53+I54+I55+I56+I57+I58+I59+I60+I61+I62+I63+I64+I65+I66+I67+I68+I69 | J70: =J43+J44+J45+J46+J47+J48+J49+J50+J51+J52+J53+J54+J55+J56+J57+J58+J59+J60+J61+J62+J63+J64+J65+J66+J67+J68+J69 | K70: =K43+K44+K45+K46+K47+K48+K49+K50+K51+K52+K53+K54+K55+K56+K57+K58+K59+K60+K61+K62+K63+K64+K65+K66+K67+K68+K69 | L70: =L43+L44+L45+L46+L47+L48+L49+L50+L51+L52+L53+L54+L55+L56+L57+L58+L59+L60+L61+L62+L63+L64+L65+L66+L67+L68+L69 | M70: =M43+M44+M45+M46+M47+M48+M49+M50+M51+M52+M53+M54+M55+M56+M57+M58+M59+M60+M61+M62+M63+M64+M65+M66+M67+M68+M69 | R70: =R43+R44+R45+R46+R47+R48+R49+R50+R51+R52+R53+R54+R55+R56+R57+R58+R59+R60+R61+R62+R63+R64+R65+R66+R67+R68+R69 | W70: =W43+W44+W45+W46+W47+W48+W49+W50+W51+W52+W53+W54+W55+W56+W57+W58+W59+W60+W61+W62+W63+W64+W65+W66+W67+W68+W69 | AC70: =AC43+AC44+AC45+AC46+AC47+AC48+AC49+AC50+AC51+AC52+AC53+AC54+AC55+AC56+AC57+AC58+AC59+AC60+AC61+AC62+AC63+AC64+AC65+AC66+AC67+AC68+AC69 | AD70: =AD43+AD44+AD45+AD46+AD47+AD48+AD49+AD50+AD51+AD52+AD53+AD54+AD55+AD56+AD57+AD58+AD59+AD60+AD61+AD62+AD63+AD64+AD65+AD66+AD67+AD68+AD69 | AI70: =AI43+AI44+AI45+AI46+AI47+AI48+AI49+AI50+AI51+AI52+AI53+AI54+AI55+AI56+AI57+AI58+AI59+AI60+AI61+AI62+AI63+AI64+AI65+AI66+AI67+AI68+AI69 | AN70: =AN43+AN44+AN45+AN46+AN47+AN48+AN49+AN50+AN51+AN52+AN53+AN54+AN55+AN56+AN57+AN58+AN59+AN60+AN61+AN62+AN63+AN64+AN65+AN66+AN67+AN68+AN69 | AT70: =AT43+AT44+AT45+AT46+AT47+AT48+AT49+AT50+AT51+AT52+AT53+AT54+AT55+AT56+AT57+AT58+AT59+AT60+AT61+AT62+AT63+AT64+AT65+AT66+AT67+AT68+AT69 | AU70: =AU43+AU44+AU45+AU46+AU47+AU48+AU49+AU50+AU51+AU52+AU53+AU54+AU55+AU56+AU57+AU58+AU59+AU60+AU61+AU62+AU63+AU64+AU65+AU66+AU67+AU68+AU69 | AZ70: =AZ43+AZ44+AZ45+AZ46+AZ47+AZ48+AZ49+AZ50+AZ51+AZ52+AZ53+AZ54+AZ55+AZ56+AZ57+AZ58+AZ59+AZ60+AZ61+AZ62+AZ63+AZ64+AZ65+AZ66+AZ67+AZ68+AZ69 | BF70: =BF43+BF44+BF45+BF46+BF47+BF48+BF49+BF50+BF51+BF52+BF53+BF54+BF55+BF56+BF57+BF58+BF59+BF60+BF61+BF62+BF63+BF64+BF65+BF66+BF67+BF68+BF69 | BK70: =BK43+BK44+BK45+BK46+BK47+BK48+BK49+BK50+BK51+BK52+BK53+BK54+BK55+BK56+BK57+BK58+BK59+BK60+BK61+BK62+BK63+BK64+BK65+BK66+BK67+BK68+BK69 | BL70: =BL43+BL44+BL45+BL46+BL47+BL48+BL49+BL50+BL51+BL52+BL53+BL54+BL55+BL56+BL57+BL58+BL59+BL60+BL61+BL62+BL63+BL64+BL65+BL66+BL67+BL68+BL69 | BQ70: =BQ43+BQ44+BQ45+BQ46+BQ47+BQ48+BQ49+BQ50+BQ51+BQ52+BQ53+BQ54+BQ55+BQ56+BQ57+BQ58+BQ59+BQ60+BQ61+BQ62+BQ63+BQ64+BQ65+BQ66+BQ67+BQ68+BQ69 | BW70: =BW43+BW44+BW45+BW46+BW47+BW48+BW49+BW50+BW51+BW52+BW53+BW54+BW55+BW56+BW57+BW58+BW59+BW60+BW61+BW62+BW63+BW64+BW65+BW66+BW67+BW68+BW69 | CB70: =CB43+CB44+CB45+CB46+CB47+CB48+CB49+CB50+CB51+CB52+CB53+CB54+CB55+CB56+CB57+CB58+CB59+CB60+CB61+CB62+CB63+CB64+CB65+CB66+CB67+CB68+CB69 | CC70: =CC43+CC44+CC45+CC46+CC47+CC48+CC49+CC50+CC51+CC52+CC53+CC54+CC55+CC56+CC57+CC58+CC59+CC60+CC61+CC62+CC63+CC64+CC65+CC66+CC67+CC68+CC69 | CD70: =CD43+CD44+CD45+CD46+CD47+CD48+CD49+CD50+CD51+CD52+CD53+CD54+CD55+CD56+CD57+CD58+CD59+CD60+CD61+CD62+CD63+CD64+CD65+CD66+CD67+CD68+CD69
A71: SETENA D1
A72: In process | B72: 3.1 | C72: Preliminary environmental study, D1 form | D72: DEHC | E72: Setena D1 | F72: STUDIES | G72: 14577 | H72: 130000 | I72: =G72+H72 | J72: =SUMIF(LEDGER!$A:$A,$B72,LEDGER!$G:$G) | K72: =I72-J72 | L72: =J72+CD72 | M72: =I72-L72 | R72: =SUM(N72:Q72) | W72: =SUM(S72:V72) | AC72: =SUM(X72:AB72) | AD72: =R72+W72+AC72 | AI72: =SUM(AE72:AH72) | AN72: =SUM(AJ72:AM72) | AT72: =SUM(AO72:AS72) | AU72: =AI72+AN72+AT72 | AV72: 35759.86 | AZ72: =SUM(AV72:AY72) | BF72: =SUM(BA72:BE72) | BK72: =SUM(BG72:BJ72) | BL72: =AZ72+BF72+BK72 | BQ72: =SUM(BM72:BP72) | BW72: =SUM(BR72:BV72) | CB72: =SUM(BX72:CA72) | CC72: =BQ72+BW72+CB72 | CD72: =AD72+AU72+BL72+CC72
A73: Approved | B73: 3.2 | C73: Register Plans with Master Plan Roads | D73: Surveyor | E73: Setena D1 | F73: ENGINEERING | G73: 8000 | H73: 30702.5 | I73: =G73+H73 | J73: =SUMIF(LEDGER!$A:$A,$B73,LEDGER!$G:$G) | K73: =I73-J73 | L73: =J73+CD73 | M73: =I73-L73 | R73: =SUM(N73:Q73) | W73: =SUM(S73:V73) | AC73: =SUM(X73:AB73) | AD73: =R73+W73+AC73 | AI73: =SUM(AE73:AH73) | AN73: =SUM(AJ73:AM73) | AT73: =SUM(AO73:AS73) | AU73: =AI73+AN73+AT73 | AZ73: =SUM(AV73:AY73) | BF73: =SUM(BA73:BE73) | BK73: =SUM(BG73:BJ73) | BL73: =AZ73+BF73+BK73 | BQ73: =SUM(BM73:BP73) | BW73: =SUM(BR73:BV73) | CB73: =SUM(BX73:CA73) | CC73: =BQ73+BW73+CB73 | CD73: =AD73+AU73+BL73+CC73
A74: In process | B74: 3.3 | C74: Hydrological study / Discharge Permit | D74: DEHC | E74: Setena D1 | F74: STUDIES | G74: 8362 | H74: 0 | I74: =G74+H74 | J74: =SUMIF(LEDGER!$A:$A,$B74,LEDGER!$G:$G) | K74: =I74-J74 | L74: =J74+CD74 | M74: =I74-L74 | R74: =SUM(N74:Q74) | W74: =SUM(S74:V74) | AC74: =SUM(X74:AB74) | AD74: =R74+W74+AC74 | AI74: =SUM(AE74:AH74) | AN74: =SUM(AJ74:AM74) | AT74: =SUM(AO74:AS74) | AU74: =AI74+AN74+AT74 | AZ74: =SUM(AV74:AY74) | BF74: =SUM(BA74:BE74) | BK74: =SUM(BG74:BJ74) | BL74: =AZ74+BF74+BK74 | BQ74: =SUM(BM74:BP74) | BW74: =SUM(BR74:BV74) | BX74: 8362 | CB74: =SUM(BX74:CA74) | CC74: =BQ74+BW74+CB74 | CD74: =AD74+AU74+BL74+CC74
A75: In process | B75: 3.4 | C75: Master plan analysis and condominium strategy | D75: DEHC | E75: Setena D1 | F75: ENGINEERING | G75: 12995 | H75: 0 | I75: =G75+H75 | J75: =SUMIF(LEDGER!$A:$A,$B75,LEDGER!$G:$G) | K75: =I75-J75 | L75: =J75+CD75 | M75: =I75-L75 | R75: =SUM(N75:Q75) | W75: =SUM(S75:V75) | AC75: =SUM(X75:AB75) | AD75: =R75+W75+AC75 | AI75: =SUM(AE75:AH75) | AJ75: 6497.5 | AN75: =SUM(AJ75:AM75) | AO75: 6497.5 | AT75: =SUM(AO75:AS75) | AU75: =AI75+AN75+AT75 | AZ75: =SUM(AV75:AY75) | BF75: =SUM(BA75:BE75) | BK75: =SUM(BG75:BJ75) | BL75: =AZ75+BF75+BK75 | BQ75: =SUM(BM75:BP75) | BW75: =SUM(BR75:BV75) | CB75: =SUM(BX75:CA75) | CC75: =BQ75+BW75+CB75 | CD75: =AD75+AU75+BL75+CC75
A76: Approved | B76: 3.5 | C76: Civil Engineering | E76: Setena D1 | F76: ENGINEERING | G76: 0 | H76: 0 | I76: =G76+H76 | J76: =SUMIF(LEDGER!$A:$A,$B76,LEDGER!$G:$G) | K76: =I76-J76 | L76: =J76+CD76 | M76: =I76-L76 | R76: =SUM(N76:Q76) | W76: =SUM(S76:V76) | AC76: =SUM(X76:AB76) | AD76: =R76+W76+AC76 | AI76: =SUM(AE76:AH76) | AN76: =SUM(AJ76:AM76) | AT76: =SUM(AO76:AS76) | AU76: =AI76+AN76+AT76 | AZ76: =SUM(AV76:AY76) | BF76: =SUM(BA76:BE76) | BK76: =SUM(BG76:BJ76) | BL76: =AZ76+BF76+BK76 | BQ76: =SUM(BM76:BP76) | BW76: =SUM(BR76:BV76) | CB76: =SUM(BX76:CA76) | CC76: =BQ76+BW76+CB76 | CD76: =AD76+AU76+BL76+CC76
A77: Approved | B77: 3.5.1 | C77: - Schematic design | D77: DEHC | E77: Setena D1 | F77: ENGINEERING | G77: 117068 | H77: 0 | I77: =G77+H77 | J77: =SUMIF(LEDGER!$A:$A,$B77,LEDGER!$G:$G) | K77: =I77-J77 | L77: =J77+CD77 | M77: =I77-L77 | R77: =SUM(N77:Q77) | W77: =SUM(S77:V77) | AC77: =SUM(X77:AB77) | AD77: =R77+W77+AC77 | AI77: =SUM(AE77:AH77) | AJ77: 20120 | AK77: 0.4 | AL77: 46827.2 | AN77: =SUM(AJ77:AM77) | AT77: =SUM(AO77:AS77) | AU77: =AI77+AN77+AT77 | AZ77: =SUM(AV77:AY77) | BF77: =SUM(BA77:BE77) | BK77: =SUM(BG77:BJ77) | BL77: =AZ77+BF77+BK77 | BQ77: =SUM(BM77:BP77) | BW77: =SUM(BR77:BV77) | CB77: =SUM(BX77:CA77) | CC77: =BQ77+BW77+CB77 | CD77: =AD77+AU77+BL77+CC77
A78: Approved | B78: 3.52 | C78: - Construction drawings & quantities | D78: DEHC | E78: Setena D1 | F78: ENGINEERING | G78: 0 | H78: 0 | I78: =G78+H78 | J78: =SUMIF(LEDGER!$A:$A,$B78,LEDGER!$G:$G) | K78: =I78-J78 | L78: =J78+CD78 | M78: =I78-L78 | R78: =SUM(N78:Q78) | W78: =SUM(S78:V78) | AC78: =SUM(X78:AB78) | AD78: =R78+W78+AC78 | AI78: =SUM(AE78:AH78) | AN78: =SUM(AJ78:AM78) | AT78: =SUM(AO78:AS78) | AU78: =AI78+AN78+AT78 | AZ78: =SUM(AV78:AY78) | BF78: =SUM(BA78:BE78) | BK78: =SUM(BG78:BJ78) | BL78: =AZ78+BF78+BK78 | BQ78: =SUM(BM78:BP78) | BW78: =SUM(BR78:BV78) | CB78: =SUM(BX78:CA78) | CC78: =BQ78+BW78+CB78 | CD78: =AD78+AU78+BL78+CC78
A79: Approved | B79: 3.6 | C79: SETENA review | D79: Government | E79: Setena D1 | F79: ENGINEERING | G79: 0 | H79: 0 | I79: =G79+H79 | J79: =SUMIF(LEDGER!$A:$A,$B79,LEDGER!$G:$G) | K79: =I79-J79 | L79: =J79+CD79 | M79: =I79-L79 | R79: =SUM(N79:Q79) | W79: =SUM(S79:V79) | AC79: =SUM(X79:AB79) | AD79: =R79+W79+AC79 | AI79: =SUM(AE79:AH79) | AN79: =SUM(AJ79:AM79) | AT79: =SUM(AO79:AS79) | AU79: =AI79+AN79+AT79 | AZ79: =SUM(AV79:AY79) | BF79: =SUM(BA79:BE79) | BK79: =SUM(BG79:BJ79) | BL79: =AZ79+BF79+BK79 | BQ79: =SUM(BM79:BP79) | BW79: =SUM(BR79:BV79) | CB79: =SUM(BX79:CA79) | CC79: =BQ79+BW79+CB79 | CD79: =AD79+AU79+BL79+CC79
A80: Approved | B80: 3.7 | C80: Annexed information / Answer Questions | D80: DEHC / Blake | E80: Setena D1 | F80: ENGINEERING | G80: 0 | H80: 0 | I80: =G80+H80 | J80: =SUMIF(LEDGER!$A:$A,$B80,LEDGER!$G:$G) | K80: =I80-J80 | L80: =J80+CD80 | M80: =I80-L80 | R80: =SUM(N80:Q80) | W80: =SUM(S80:V80) | AC80: =SUM(X80:AB80) | AD80: =R80+W80+AC80 | AI80: =SUM(AE80:AH80) | AN80: =SUM(AJ80:AM80) | AT80: =SUM(AO80:AS80) | AU80: =AI80+AN80+AT80 | AZ80: =SUM(AV80:AY80) | BF80: =SUM(BA80:BE80) | BK80: =SUM(BG80:BJ80) | BL80: =AZ80+BF80+BK80 | BQ80: =SUM(BM80:BP80) | BW80: =SUM(BR80:BV80) | CB80: =SUM(BX80:CA80) | CC80: =BQ80+BW80+CB80 | CD80: =AD80+AU80+BL80+CC80
A81: Approved | B81: 3.8 | C81: SETENA Final review | D81: Blake | E81: Setena D1 | F81: GOV | G81: 0 | H81: 0 | I81: =G81+H81 | J81: =SUMIF(LEDGER!$A:$A,$B81,LEDGER!$G:$G) | K81: =I81-J81 | L81: =J81+CD81 | M81: =I81-L81 | R81: =SUM(N81:Q81) | W81: =SUM(S81:V81) | AC81: =SUM(X81:AB81) | AD81: =R81+W81+AC81 | AI81: =SUM(AE81:AH81) | AN81: =SUM(AJ81:AM81) | AT81: =SUM(AO81:AS81) | AU81: =AI81+AN81+AT81 | AZ81: =SUM(AV81:AY81) | BF81: =SUM(BA81:BE81) | BK81: =SUM(BG81:BJ81) | BL81: =AZ81+BF81+BK81 | BQ81: =SUM(BM81:BP81) | BW81: =SUM(BR81:BV81) | CB81: =SUM(BX81:CA81) | CC81: =BQ81+BW81+CB81 | CD81: =AD81+AU81+BL81+CC81
A82: Approved | B82: 3.9 | C82: SETENA (VA) Approval | D82: DEHC / Blake | E82: Setena D1 | F82: ENGINEERING | G82: 1457.7 | H82: 0 | I82: =G82+H82 | J82: =SUMIF(LEDGER!$A:$A,$B82,LEDGER!$G:$G) | K82: =I82-J82 | L82: =J82+CD82 | M82: =I82-L82 | R82: =SUM(N82:Q82) | W82: =SUM(S82:V82) | AC82: =SUM(X82:AB82) | AD82: =R82+W82+AC82 | AI82: =SUM(AE82:AH82) | AN82: =SUM(AJ82:AM82) | AT82: =SUM(AO82:AS82) | AU82: =AI82+AN82+AT82 | AZ82: =SUM(AV82:AY82) | BF82: =SUM(BA82:BE82) | BK82: =SUM(BG82:BJ82) | BL82: =AZ82+BF82+BK82 | BQ82: =SUM(BM82:BP82) | BS82: 1457.7 | BW82: =SUM(BR82:BV82) | CB82: =SUM(BX82:CA82) | CC82: =BQ82+BW82+CB82 | CD82: =AD82+AU82+BL82+CC82
A83: Approved | B83: 3.101 | C83: Treatment Plant | D83: Treatment Plant Eng. | E83: Setena D1 | F83: GOV | G83: 50000 | H83: 0 | I83: =G83+H83 | J83: =SUMIF(LEDGER!$A:$A,$B83,LEDGER!$G:$G) | K83: =I83-J83 | L83: =J83+CD83 | M83: =I83-L83 | R83: =SUM(N83:Q83) | W83: =SUM(S83:V83) | AC83: =SUM(X83:AB83) | AD83: =R83+W83+AC83 | AI83: =SUM(AE83:AH83) | AN83: =SUM(AJ83:AM83) | AT83: =SUM(AO83:AS83) | AU83: =AI83+AN83+AT83 | AZ83: =SUM(AV83:AY83) | BF83: =SUM(BA83:BE83) | BK83: =SUM(BG83:BJ83) | BL83: =AZ83+BF83+BK83 | BQ83: =SUM(BM83:BP83) | BV83: 25000 | BW83: =SUM(BR83:BV83) | BX83: 25000 | CB83: =SUM(BX83:CA83) | CC83: =BQ83+BW83+CB83 | CD83: =AD83+AU83+BL83+CC83
A84: Approved | B84: 3.11 | C84: Superficial infiltration test | D84: Complete | E84: Setena D1 | F84: GOV | G84: 0 | H84: 0 | I84: =G84+H84 | J84: =SUMIF(LEDGER!$A:$A,$B84,LEDGER!$G:$G) | K84: =I84-J84 | L84: =J84+CD84 | M84: =I84-L84 | R84: =SUM(N84:Q84) | W84: =SUM(S84:V84) | AC84: =SUM(X84:AB84) | AD84: =R84+W84+AC84 | AI84: =SUM(AE84:AH84) | AN84: =SUM(AJ84:AM84) | AT84: =SUM(AO84:AS84) | AU84: =AI84+AN84+AT84 | AZ84: =SUM(AV84:AY84) | BF84: =SUM(BA84:BE84) | BK84: =SUM(BG84:BJ84) | BL84: =AZ84+BF84+BK84 | BQ84: =SUM(BM84:BP84) | BW84: =SUM(BR84:BV84) | CB84: =SUM(BX84:CA84) | CC84: =BQ84+BW84+CB84 | CD84: =AD84+AU84+BL84+CC84
A85: Approved | B85: 4.1 | C85: Water Source Strategy | D85: Blake | E85: Setena D1 | F85: WATER | G85: 0 | H85: 0 | I85: =G85+H85 | J85: =SUMIF(LEDGER!$A:$A,$B85,LEDGER!$G:$G) | K85: =I85-J85 | L85: =J85+CD85 | M85: =I85-L85 | R85: =SUM(N85:Q85) | W85: =SUM(S85:V85) | AC85: =SUM(X85:AB85) | AD85: =R85+W85+AC85 | AI85: =SUM(AE85:AH85) | AN85: =SUM(AJ85:AM85) | AT85: =SUM(AO85:AS85) | AU85: =AI85+AN85+AT85 | AZ85: =SUM(AV85:AY85) | BF85: =SUM(BA85:BE85) | BK85: =SUM(BG85:BJ85) | BL85: =AZ85+BF85+BK85 | BQ85: =SUM(BM85:BP85) | BW85: =SUM(BR85:BV85) | CB85: =SUM(BX85:CA85) | CC85: =BQ85+BW85+CB85 | CD85: =AD85+AU85+BL85+CC85
A86: Approved | B86: 4.2.1 | C86: Water Department Negotiations | D86: Blake | E86: Setena D1 | F86: WATER | G86: 0 | H86: 0 | I86: =G86+H86 | J86: =SUMIF(LEDGER!$A:$A,$B86,LEDGER!$G:$G) | K86: =I86-J86 | L86: =J86+CD86 | M86: =I86-L86 | R86: =SUM(N86:Q86) | W86: =SUM(S86:V86) | AC86: =SUM(X86:AB86) | AD86: =R86+W86+AC86 | AI86: =SUM(AE86:AH86) | AN86: =SUM(AJ86:AM86) | AT86: =SUM(AO86:AS86) | AU86: =AI86+AN86+AT86 | AZ86: =SUM(AV86:AY86) | BF86: =SUM(BA86:BE86) | BK86: =SUM(BG86:BJ86) | BL86: =AZ86+BF86+BK86 | BQ86: =SUM(BM86:BP86) | BW86: =SUM(BR86:BV86) | CB86: =SUM(BX86:CA86) | CC86: =BQ86+BW86+CB86 | CD86: =AD86+AU86+BL86+CC86
A87: Approved | B87: 4.2.2 | C87: Water Department Installation (We pay and Donate) | D87: Sierra | E87: Setena D1 | F87: WATER | G87: 50000 | H87: 0 | I87: =G87+H87 | J87: =SUMIF(LEDGER!$A:$A,$B87,LEDGER!$G:$G) | K87: =I87-J87 | L87: =J87+CD87 | M87: =I87-L87 | R87: =SUM(N87:Q87) | W87: =SUM(S87:V87) | AC87: =SUM(X87:AB87) | AD87: =R87+W87+AC87 | AI87: =SUM(AE87:AH87) | AM87: 25000 | AN87: =SUM(AJ87:AM87) | AR87: 25000 | AT87: =SUM(AO87:AS87) | AU87: =AI87+AN87+AT87 | AZ87: =SUM(AV87:AY87) | BF87: =SUM(BA87:BE87) | BK87: =SUM(BG87:BJ87) | BL87: =AZ87+BF87+BK87 | BQ87: =SUM(BM87:BP87) | BW87: =SUM(BR87:BV87) | CB87: =SUM(BX87:CA87) | CC87: =BQ87+BW87+CB87 | CD87: =AD87+AU87+BL87+CC87
A88: Approved | B88: 4.2.3 | C88: Water Department System Installation | D88: Aguatech | E88: Setena D1 | F88: WATER | G88: 150000 | H88: 0 | I88: =G88+H88 | J88: =SUMIF(LEDGER!$A:$A,$B88,LEDGER!$G:$G) | K88: =I88-J88 | L88: =J88+CD88 | M88: =I88-L88 | R88: =SUM(N88:Q88) | W88: =SUM(S88:V88) | AC88: =SUM(X88:AB88) | AD88: =R88+W88+AC88 | AI88: =SUM(AE88:AH88) | AN88: =SUM(AJ88:AM88) | AT88: =SUM(AO88:AS88) | AU88: =AI88+AN88+AT88 | AZ88: =SUM(AV88:AY88) | BF88: =SUM(BA88:BE88) | BK88: =SUM(BG88:BJ88) | BL88: =AZ88+BF88+BK88 | BQ88: =SUM(BM88:BP88) | BW88: =SUM(BR88:BV88) | CB88: =SUM(BX88:CA88) | CC88: =BQ88+BW88+CB88 | CD88: =AD88+AU88+BL88+CC88
A89: Approved | B89: 4.3 | C89: Spring Concession (Based on Strategy) | D89: Blake | E89: Setena D1 | F89: WATER | G89: 0 | H89: 0 | I89: =G89+H89 | J89: =SUMIF(LEDGER!$A:$A,$B89,LEDGER!$G:$G) | K89: =I89-J89 | L89: =J89+CD89 | M89: =I89-L89 | R89: =SUM(N89:Q89) | W89: =SUM(S89:V89) | AC89: =SUM(X89:AB89) | AD89: =R89+W89+AC89 | AI89: =SUM(AE89:AH89) | AN89: =SUM(AJ89:AM89) | AT89: =SUM(AO89:AS89) | AU89: =AI89+AN89+AT89 | AZ89: =SUM(AV89:AY89) | BF89: =SUM(BA89:BE89) | BK89: =SUM(BG89:BJ89) | BL89: =AZ89+BF89+BK89 | BQ89: =SUM(BM89:BP89) | BW89: =SUM(BR89:BV89) | CB89: =SUM(BX89:CA89) | CC89: =BQ89+BW89+CB89 | CD89: =AD89+AU89+BL89+CC89
A90: In process | B90: 4.4 | C90: Deep Well Concession / Casing x 2 Wells | D90: PV Drilling | E90: Setena D1 | F90: WATER | G90: 126227 | H90: 0 | I90: =G90+H90 | J90: =SUMIF(LEDGER!$A:$A,$B90,LEDGER!$G:$G) | K90: =I90-J90 | L90: =J90+CD90 | M90: =I90-L90 | R90: =SUM(N90:Q90) | W90: =SUM(S90:V90) | AC90: =SUM(X90:AB90) | AD90: =R90+W90+AC90 | AI90: =SUM(AE90:AH90) | AN90: =SUM(AJ90:AM90) | AT90: =SUM(AO90:AS90) | AU90: =AI90+AN90+AT90 | AZ90: =SUM(AV90:AY90) | BF90: =SUM(BA90:BE90) | BK90: =SUM(BG90:BJ90) | BL90: =AZ90+BF90+BK90 | BQ90: =SUM(BM90:BP90) | BW90: =SUM(BR90:BV90) | CB90: =SUM(BX90:CA90) | CC90: =BQ90+BW90+CB90 | CD90: =AD90+AU90+BL90+CC90
A91: Approved | B91: 8.1 | C91: Water Department Negotiations | D91: Blake | E91: Setena D1 | F91: Phase 1 | G91: 28250 | H91: 0 | I91: =G91+H91 | J91: =SUMIF(LEDGER!$A:$A,$B91,LEDGER!$G:$G) | K91: =I91-J91 | L91: =J91+CD91 | M91: =I91-L91 | R91: =SUM(N91:Q91) | W91: =SUM(S91:V91) | AC91: =SUM(X91:AB91) | AD91: =R91+W91+AC91 | AI91: =SUM(AE91:AH91) | AN91: =SUM(AJ91:AM91) | AO91: 28250 | AT91: =SUM(AO91:AS91) | AU91: =AI91+AN91+AT91 | AZ91: =SUM(AV91:AY91) | BF91: =SUM(BA91:BE91) | BK91: =SUM(BG91:BJ91) | BL91: =AZ91+BF91+BK91 | BQ91: =SUM(BM91:BP91) | BW91: =SUM(BR91:BV91) | CB91: =SUM(BX91:CA91) | CC91: =BQ91+BW91+CB91 | CD91: =AD91+AU91+BL91+CC91
A92: Approved | B92: 8.2 | C92: SETENA (VA) Approval | D92: Blake | E92: Setena D1 | F92: Phase 1 | G92: 42375 | H92: 0 | I92: =G92+H92 | J92: =SUMIF(LEDGER!$A:$A,$B92,LEDGER!$G:$G) | K92: =I92-J92 | L92: =J92+CD92 | M92: =I92-L92 | R92: =SUM(N92:Q92) | W92: =SUM(S92:V92) | AC92: =SUM(X92:AB92) | AD92: =R92+W92+AC92 | AI92: =SUM(AE92:AH92) | AN92: =SUM(AJ92:AM92) | AT92: =SUM(AO92:AS92) | AU92: =AI92+AN92+AT92 | AZ92: =SUM(AV92:AY92) | BF92: =SUM(BA92:BE92) | BK92: =SUM(BG92:BJ92) | BL92: =AZ92+BF92+BK92 | BQ92: =SUM(BM92:BP92) | BW92: =SUM(BR92:BV92) | CA92: 42375 | CB92: =SUM(BX92:CA92) | CC92: =BQ92+BW92+CB92 | CD92: =AD92+AU92+BL92+CC92
A93: Approved | B93: 8.4 | C93: Obtain Beach Club Permits | D93: Blake | E93: Setena D1 | F93: BEACH CLUB P1 | G93: 14125 | H93: 0 | I93: =G93+H93 | J93: =SUMIF(LEDGER!$A:$A,$B93,LEDGER!$G:$G) | K93: =I93-J93 | L93: =J93+CD93 | M93: =I93-L93 | R93: =SUM(N93:Q93) | W93: =SUM(S93:V93) | AC93: =SUM(X93:AB93) | AD93: =R93+W93+AC93 | AI93: =SUM(AE93:AH93) | AN93: =SUM(AJ93:AM93) | AT93: =SUM(AO93:AS93) | AU93: =AI93+AN93+AT93 | AZ93: =SUM(AV93:AY93) | BF93: =SUM(BA93:BE93) | BG93: 14125 | BK93: =SUM(BG93:BJ93) | BL93: =AZ93+BF93+BK93 | BQ93: =SUM(BM93:BP93) | BW93: =SUM(BR93:BV93) | CB93: =SUM(BX93:CA93) | CC93: =BQ93+BW93+CB93 | CD93: =AD93+AU93+BL93+CC93
C94: TOTAL Setena D1 | G94: =G72+G73+G74+G75+G76+G77+G78+G79+G80+G81+G82+G83+G84+G85+G86+G87+G88+G89+G90+G91+G92+G93 | H94: =H72+H73+H74+H75+H76+H77+H78+H79+H80+H81+H82+H83+H84+H85+H86+H87+H88+H89+H90+H91+H92+H93 | I94: =I72+I73+I74+I75+I76+I77+I78+I79+I80+I81+I82+I83+I84+I85+I86+I87+I88+I89+I90+I91+I92+I93 | J94: =J72+J73+J74+J75+J76+J77+J78+J79+J80+J81+J82+J83+J84+J85+J86+J87+J88+J89+J90+J91+J92+J93 | K94: =K72+K73+K74+K75+K76+K77+K78+K79+K80+K81+K82+K83+K84+K85+K86+K87+K88+K89+K90+K91+K92+K93 | L94: =L72+L73+L74+L75+L76+L77+L78+L79+L80+L81+L82+L83+L84+L85+L86+L87+L88+L89+L90+L91+L92+L93 | M94: =M72+M73+M74+M75+M76+M77+M78+M79+M80+M81+M82+M83+M84+M85+M86+M87+M88+M89+M90+M91+M92+M93 | R94: =R72+R73+R74+R75+R76+R77+R78+R79+R80+R81+R82+R83+R84+R85+R86+R87+R88+R89+R90+R91+R92+R93 | W94: =W72+W73+W74+W75+W76+W77+W78+W79+W80+W81+W82+W83+W84+W85+W86+W87+W88+W89+W90+W91+W92+W93 | AC94: =AC72+AC73+AC74+AC75+AC76+AC77+AC78+AC79+AC80+AC81+AC82+AC83+AC84+AC85+AC86+AC87+AC88+AC89+AC90+AC91+AC92+AC93 | AD94: =AD72+AD73+AD74+AD75+AD76+AD77+AD78+AD79+AD80+AD81+AD82+AD83+AD84+AD85+AD86+AD87+AD88+AD89+AD90+AD91+AD92+AD93 | AI94: =AI72+AI73+AI74+AI75+AI76+AI77+AI78+AI79+AI80+AI81+AI82+AI83+AI84+AI85+AI86+AI87+AI88+AI89+AI90+AI91+AI92+AI93 | AN94: =AN72+AN73+AN74+AN75+AN76+AN77+AN78+AN79+AN80+AN81+AN82+AN83+AN84+AN85+AN86+AN87+AN88+AN89+AN90+AN91+AN92+AN93 | AT94: =AT72+AT73+AT74+AT75+AT76+AT77+AT78+AT79+AT80+AT81+AT82+AT83+AT84+AT85+AT86+AT87+AT88+AT89+AT90+AT91+AT92+AT93 | AU94: =AU72+AU73+AU74+AU75+AU76+AU77+AU78+AU79+AU80+AU81+AU82+AU83+AU84+AU85+AU86+AU87+AU88+AU89+AU90+AU91+AU92+AU93 | AZ94: =AZ72+AZ73+AZ74+AZ75+AZ76+AZ77+AZ78+AZ79+AZ80+AZ81+AZ82+AZ83+AZ84+AZ85+AZ86+AZ87+AZ88+AZ89+AZ90+AZ91+AZ92+AZ93 | BF94: =BF72+BF73+BF74+BF75+BF76+BF77+BF78+BF79+BF80+BF81+BF82+BF83+BF84+BF85+BF86+BF87+BF88+BF89+BF90+BF91+BF92+BF93 | BK94: =BK72+BK73+BK74+BK75+BK76+BK77+BK78+BK79+BK80+BK81+BK82+BK83+BK84+BK85+BK86+BK87+BK88+BK89+BK90+BK91+BK92+BK93 | BL94: =BL72+BL73+BL74+BL75+BL76+BL77+BL78+BL79+BL80+BL81+BL82+BL83+BL84+BL85+BL86+BL87+BL88+BL89+BL90+BL91+BL92+BL93 | BQ94: =BQ72+BQ73+BQ74+BQ75+BQ76+BQ77+BQ78+BQ79+BQ80+BQ81+BQ82+BQ83+BQ84+BQ85+BQ86+BQ87+BQ88+BQ89+BQ90+BQ91+BQ92+BQ93 | BW94: =BW72+BW73+BW74+BW75+BW76+BW77+BW78+BW79+BW80+BW81+BW82+BW83+BW84+BW85+BW86+BW87+BW88+BW89+BW90+BW91+BW92+BW93 | CB94: =CB72+CB73+CB74+CB75+CB76+CB77+CB78+CB79+CB80+CB81+CB82+CB83+CB84+CB85+CB86+CB87+CB88+CB89+CB90+CB91+CB92+CB93 | CC94: =CC72+CC73+CC74+CC75+CC76+CC77+CC78+CC79+CC80+CC81+CC82+CC83+CC84+CC85+CC86+CC87+CC88+CC89+CC90+CC91+CC92+CC93 | CD94: =CD72+CD73+CD74+CD75+CD76+CD77+CD78+CD79+CD80+CD81+CD82+CD83+CD84+CD85+CD86+CD87+CD88+CD89+CD90+CD91+CD92+CD93
A95: SIN CATEGORÍA
A96: Approved | B96: 7.1 | C96: Project information | D96: Blake | E96: Sin categoría | G96: 0 | H96: 0 | I96: =G96+H96 | J96: =SUMIF(LEDGER!$A:$A,$B96,LEDGER!$G:$G) | K96: =I96-J96 | L96: =J96+CD96 | M96: =I96-L96 | R96: =SUM(N96:Q96) | W96: =SUM(S96:V96) | AC96: =SUM(X96:AB96) | AD96: =R96+W96+AC96 | AI96: =SUM(AE96:AH96) | AN96: =SUM(AJ96:AM96) | AT96: =SUM(AO96:AS96) | AU96: =AI96+AN96+AT96 | AZ96: =SUM(AV96:AY96) | BF96: =SUM(BA96:BE96) | BK96: =SUM(BG96:BJ96) | BL96: =AZ96+BF96+BK96 | BQ96: =SUM(BM96:BP96) | BW96: =SUM(BR96:BV96) | CB96: =SUM(BX96:CA96) | CC96: =BQ96+BW96+CB96 | CD96: =AD96+AU96+BL96+CC96
C97: TOTAL Sin categoría | G97: =G96 | H97: =H96 | I97: =I96 | J97: =J96 | K97: =K96 | L97: =L96 | M97: =M96 | R97: =R96 | W97: =W96 | AC97: =AC96 | AD97: =AD96 | AI97: =AI96 | AN97: =AN96 | AT97: =AT96 | AU97: =AU96 | AZ97: =AZ96 | BF97: =BF96 | BK97: =BK96 | BL97: =BL96 | BQ97: =BQ96 | BW97: =BW96 | CB97: =CB96 | CC97: =CC96 | CD97: =CD96
C98: PROJECT TOTAL | G98: =G8+G9+G12+G13+G14+G15+G16+G19+G20+G21+G22+G23+G24+G25+G26+G27+G28+G29+G32+G33+G34+G35+G36+G37+G38+G39+G40+G43+G44+G45+G46+G47+G48+G49+G50+G51+G52+G53+G54+G55+G56+G57+G58+G59+G60+G61+G62+G63+G64+G65+G66+G67+G68+G69+G72+G73+G74+G75+G76+G77+G78+G79+G80+G81+G82+G83+G84+G85+G86+G87+G88+G89+G90+G91+G92+G93+G96 | H98: =H8+H9+H12+H13+H14+H15+H16+H19+H20+H21+H22+H23+H24+H25+H26+H27+H28+H29+H32+H33+H34+H35+H36+H37+H38+H39+H40+H43+H44+H45+H46+H47+H48+H49+H50+H51+H52+H53+H54+H55+H56+H57+H58+H59+H60+H61+H62+H63+H64+H65+H66+H67+H68+H69+H72+H73+H74+H75+H76+H77+H78+H79+H80+H81+H82+H83+H84+H85+H86+H87+H88+H89+H90+H91+H92+H93+H96 | I98: =I8+I9+I12+I13+I14+I15+I16+I19+I20+I21+I22+I23+I24+I25+I26+I27+I28+I29+I32+I33+I34+I35+I36+I37+I38+I39+I40+I43+I44+I45+I46+I47+I48+I49+I50+I51+I52+I53+I54+I55+I56+I57+I58+I59+I60+I61+I62+I63+I64+I65+I66+I67+I68+I69+I72+I73+I74+I75+I76+I77+I78+I79+I80+I81+I82+I83+I84+I85+I86+I87+I88+I89+I90+I91+I92+I93+I96 | J98: =J8+J9+J12+J13+J14+J15+J16+J19+J20+J21+J22+J23+J24+J25+J26+J27+J28+J29+J32+J33+J34+J35+J36+J37+J38+J39+J40+J43+J44+J45+J46+J47+J48+J49+J50+J51+J52+J53+J54+J55+J56+J57+J58+J59+J60+J61+J62+J63+J64+J65+J66+J67+J68+J69+J72+J73+J74+J75+J76+J77+J78+J79+J80+J81+J82+J83+J84+J85+J86+J87+J88+J89+J90+J91+J92+J93+J96 | K98: =K8+K9+K12+K13+K14+K15+K16+K19+K20+K21+K22+K23+K24+K25+K26+K27+K28+K29+K32+K33+K34+K35+K36+K37+K38+K39+K40+K43+K44+K45+K46+K47+K48+K49+K50+K51+K52+K53+K54+K55+K56+K57+K58+K59+K60+K61+K62+K63+K64+K65+K66+K67+K68+K69+K72+K73+K74+K75+K76+K77+K78+K79+K80+K81+K82+K83+K84+K85+K86+K87+K88+K89+K90+K91+K92+K93+K96 | L98: =L8+L9+L12+L13+L14+L15+L16+L19+L20+L21+L22+L23+L24+L25+L26+L27+L28+L29+L32+L33+L34+L35+L36+L37+L38+L39+L40+L43+L44+L45+L46+L47+L48+L49+L50+L51+L52+L53+L54+L55+L56+L57+L58+L59+L60+L61+L62+L63+L64+L65+L66+L67+L68+L69+L72+L73+L74+L75+L76+L77+L78+L79+L80+L81+L82+L83+L84+L85+L86+L87+L88+L89+L90+L91+L92+L93+L96 | M98: =M8+M9+M12+M13+M14+M15+M16+M19+M20+M21+M22+M23+M24+M25+M26+M27+M28+M29+M32+M33+M34+M35+M36+M37+M38+M39+M40+M43+M44+M45+M46+M47+M48+M49+M50+M51+M52+M53+M54+M55+M56+M57+M58+M59+M60+M61+M62+M63+M64+M65+M66+M67+M68+M69+M72+M73+M74+M75+M76+M77+M78+M79+M80+M81+M82+M83+M84+M85+M86+M87+M88+M89+M90+M91+M92+M93+M96 | R98: =R8+R9+R12+R13+R14+R15+R16+R19+R20+R21+R22+R23+R24+R25+R26+R27+R28+R29+R32+R33+R34+R35+R36+R37+R38+R39+R40+R43+R44+R45+R46+R47+R48+R49+R50+R51+R52+R53+R54+R55+R56+R57+R58+R59+R60+R61+R62+R63+R64+R65+R66+R67+R68+R69+R72+R73+R74+R75+R76+R77+R78+R79+R80+R81+R82+R83+R84+R85+R86+R87+R88+R89+R90+R91+R92+R93+R96 | W98: =W8+W9+W12+W13+W14+W15+W16+W19+W20+W21+W22+W23+W24+W25+W26+W27+W28+W29+W32+W33+W34+W35+W36+W37+W38+W39+W40+W43+W44+W45+W46+W47+W48+W49+W50+W51+W52+W53+W54+W55+W56+W57+W58+W59+W60+W61+W62+W63+W64+W65+W66+W67+W68+W69+W72+W73+W74+W75+W76+W77+W78+W79+W80+W81+W82+W83+W84+W85+W86+W87+W88+W89+W90+W91+W92+W93+W96 | AC98: =AC8+AC9+AC12+AC13+AC14+AC15+AC16+AC19+AC20+AC21+AC22+AC23+AC24+AC25+AC26+AC27+AC28+AC29+AC32+AC33+AC34+AC35+AC36+AC37+AC38+AC39+AC40+AC43+AC44+AC45+AC46+AC47+AC48+AC49+AC50+AC51+AC52+AC53+AC54+AC55+AC56+AC57+AC58+AC59+AC60+AC61+AC62+AC63+AC64+AC65+AC66+AC67+AC68+AC69+AC72+AC73+AC74+AC75+AC76+AC77+AC78+AC79+AC80+AC81+AC82+AC83+AC84+AC85+AC86+AC87+AC88+AC89+AC90+AC91+AC92+AC93+AC96 | AD98: =AD8+AD9+AD12+AD13+AD14+AD15+AD16+AD19+AD20+AD21+AD22+AD23+AD24+AD25+AD26+AD27+AD28+AD29+AD32+AD33+AD34+AD35+AD36+AD37+AD38+AD39+AD40+AD43+AD44+AD45+AD46+AD47+AD48+AD49+AD50+AD51+AD52+AD53+AD54+AD55+AD56+AD57+AD58+AD59+AD60+AD61+AD62+AD63+AD64+AD65+AD66+AD67+AD68+AD69+AD72+AD73+AD74+AD75+AD76+AD77+AD78+AD79+AD80+AD81+AD82+AD83+AD84+AD85+AD86+AD87+AD88+AD89+AD90+AD91+AD92+AD93+AD96 | AI98: =AI8+AI9+AI12+AI13+AI14+AI15+AI16+AI19+AI20+AI21+AI22+AI23+AI24+AI25+AI26+AI27+AI28+AI29+AI32+AI33+AI34+AI35+AI36+AI37+AI38+AI39+AI40+AI43+AI44+AI45+AI46+AI47+AI48+AI49+AI50+AI51+AI52+AI53+AI54+AI55+AI56+AI57+AI58+AI59+AI60+AI61+AI62+AI63+AI64+AI65+AI66+AI67+AI68+AI69+AI72+AI73+AI74+AI75+AI76+AI77+AI78+AI79+AI80+AI81+AI82+AI83+AI84+AI85+AI86+AI87+AI88+AI89+AI90+AI91+AI92+AI93+AI96 | AN98: =AN8+AN9+AN12+AN13+AN14+AN15+AN16+AN19+AN20+AN21+AN22+AN23+AN24+AN25+AN26+AN27+AN28+AN29+AN32+AN33+AN34+AN35+AN36+AN37+AN38+AN39+AN40+AN43+AN44+AN45+AN46+AN47+AN48+AN49+AN50+AN51+AN52+AN53+AN54+AN55+AN56+AN57+AN58+AN59+AN60+AN61+AN62+AN63+AN64+AN65+AN66+AN67+AN68+AN69+AN72+AN73+AN74+AN75+AN76+AN77+AN78+AN79+AN80+AN81+AN82+AN83+AN84+AN85+AN86+AN87+AN88+AN89+AN90+AN91+AN92+AN93+AN96 | AT98: =AT8+AT9+AT12+AT13+AT14+AT15+AT16+AT19+AT20+AT21+AT22+AT23+AT24+AT25+AT26+AT27+AT28+AT29+AT32+AT33+AT34+AT35+AT36+AT37+AT38+AT39+AT40+AT43+AT44+AT45+AT46+AT47+AT48+AT49+AT50+AT51+AT52+AT53+AT54+AT55+AT56+AT57+AT58+AT59+AT60+AT61+AT62+AT63+AT64+AT65+AT66+AT67+AT68+AT69+AT72+AT73+AT74+AT75+AT76+AT77+AT78+AT79+AT80+AT81+AT82+AT83+AT84+AT85+AT86+AT87+AT88+AT89+AT90+AT91+AT92+AT93+AT96 | AU98: =AU8+AU9+AU12+AU13+AU14+AU15+AU16+AU19+AU20+AU21+AU22+AU23+AU24+AU25+AU26+AU27+AU28+AU29+AU32+AU33+AU34+AU35+AU36+AU37+AU38+AU39+AU40+AU43+AU44+AU45+AU46+AU47+AU48+AU49+AU50+AU51+AU52+AU53+AU54+AU55+AU56+AU57+AU58+AU59+AU60+AU61+AU62+AU63+AU64+AU65+AU66+AU67+AU68+AU69+AU72+AU73+AU74+AU75+AU76+AU77+AU78+AU79+AU80+AU81+AU82+AU83+AU84+AU85+AU86+AU87+AU88+AU89+AU90+AU91+AU92+AU93+AU96 | AZ98: =AZ8+AZ9+AZ12+AZ13+AZ14+AZ15+AZ16+AZ19+AZ20+AZ21+AZ22+AZ23+AZ24+AZ25+AZ26+AZ27+AZ28+AZ29+AZ32+AZ33+AZ34+AZ35+AZ36+AZ37+AZ38+AZ39+AZ40+AZ43+AZ44+AZ45+AZ46+AZ47+AZ48+AZ49+AZ50+AZ51+AZ52+AZ53+AZ54+AZ55+AZ56+AZ57+AZ58+AZ59+AZ60+AZ61+AZ62+AZ63+AZ64+AZ65+AZ66+AZ67+AZ68+AZ69+AZ72+AZ73+AZ74+AZ75+AZ76+AZ77+AZ78+AZ79+AZ80+AZ81+AZ82+AZ83+AZ84+AZ85+AZ86+AZ87+AZ88+AZ89+AZ90+AZ91+AZ92+AZ93+AZ96 | BF98: =BF8+BF9+BF12+BF13+BF14+BF15+BF16+BF19+BF20+BF21+BF22+BF23+BF24+BF25+BF26+BF27+BF28+BF29+BF32+BF33+BF34+BF35+BF36+BF37+BF38+BF39+BF40+BF43+BF44+BF45+BF46+BF47+BF48+BF49+BF50+BF51+BF52+BF53+BF54+BF55+BF56+BF57+BF58+BF59+BF60+BF61+BF62+BF63+BF64+BF65+BF66+BF67+BF68+BF69+BF72+BF73+BF74+BF75+BF76+BF77+BF78+BF79+BF80+BF81+BF82+BF83+BF84+BF85+BF86+BF87+BF88+BF89+BF90+BF91+BF92+BF93+BF96 | BK98: =BK8+BK9+BK12+BK13+BK14+BK15+BK16+BK19+BK20+BK21+BK22+BK23+BK24+BK25+BK26+BK27+BK28+BK29+BK32+BK33+BK34+BK35+BK36+BK37+BK38+BK39+BK40+BK43+BK44+BK45+BK46+BK47+BK48+BK49+BK50+BK51+BK52+BK53+BK54+BK55+BK56+BK57+BK58+BK59+BK60+BK61+BK62+BK63+BK64+BK65+BK66+BK67+BK68+BK69+BK72+BK73+BK74+BK75+BK76+BK77+BK78+BK79+BK80+BK81+BK82+BK83+BK84+BK85+BK86+BK87+BK88+BK89+BK90+BK91+BK92+BK93+BK96 | BL98: =BL8+BL9+BL12+BL13+BL14+BL15+BL16+BL19+BL20+BL21+BL22+BL23+BL24+BL25+BL26+BL27+BL28+BL29+BL32+BL33+BL34+BL35+BL36+BL37+BL38+BL39+BL40+BL43+BL44+BL45+BL46+BL47+BL48+BL49+BL50+BL51+BL52+BL53+BL54+BL55+BL56+BL57+BL58+BL59+BL60+BL61+BL62+BL63+BL64+BL65+BL66+BL67+BL68+BL69+BL72+BL73+BL74+BL75+BL76+BL77+BL78+BL79+BL80+BL81+BL82+BL83+BL84+BL85+BL86+BL87+BL88+BL89+BL90+BL91+BL92+BL93+BL96 | BQ98: =BQ8+BQ9+BQ12+BQ13+BQ14+BQ15+BQ16+BQ19+BQ20+BQ21+BQ22+BQ23+BQ24+BQ25+BQ26+BQ27+BQ28+BQ29+BQ32+BQ33+BQ34+BQ35+BQ36+BQ37+BQ38+BQ39+BQ40+BQ43+BQ44+BQ45+BQ46+BQ47+BQ48+BQ49+BQ50+BQ51+BQ52+BQ53+BQ54+BQ55+BQ56+BQ57+BQ58+BQ59+BQ60+BQ61+BQ62+BQ63+BQ64+BQ65+BQ66+BQ67+BQ68+BQ69+BQ72+BQ73+BQ74+BQ75+BQ76+BQ77+BQ78+BQ79+BQ80+BQ81+BQ82+BQ83+BQ84+BQ85+BQ86+BQ87+BQ88+BQ89+BQ90+BQ91+BQ92+BQ93+BQ96 | BW98: =BW8+BW9+BW12+BW13+BW14+BW15+BW16+BW19+BW20+BW21+BW22+BW23+BW24+BW25+BW26+BW27+BW28+BW29+BW32+BW33+BW34+BW35+BW36+BW37+BW38+BW39+BW40+BW43+BW44+BW45+BW46+BW47+BW48+BW49+BW50+BW51+BW52+BW53+BW54+BW55+BW56+BW57+BW58+BW59+BW60+BW61+BW62+BW63+BW64+BW65+BW66+BW67+BW68+BW69+BW72+BW73+BW74+BW75+BW76+BW77+BW78+BW79+BW80+BW81+BW82+BW83+BW84+BW85+BW86+BW87+BW88+BW89+BW90+BW91+BW92+BW93+BW96 | CB98: =CB8+CB9+CB12+CB13+CB14+CB15+CB16+CB19+CB20+CB21+CB22+CB23+CB24+CB25+CB26+CB27+CB28+CB29+CB32+CB33+CB34+CB35+CB36+CB37+CB38+CB39+CB40+CB43+CB44+CB45+CB46+CB47+CB48+CB49+CB50+CB51+CB52+CB53+CB54+CB55+CB56+CB57+CB58+CB59+CB60+CB61+CB62+CB63+CB64+CB65+CB66+CB67+CB68+CB69+CB72+CB73+CB74+CB75+CB76+CB77+CB78+CB79+CB80+CB81+CB82+CB83+CB84+CB85+CB86+CB87+CB88+CB89+CB90+CB91+CB92+CB93+CB96 | CC98: =CC8+CC9+CC12+CC13+CC14+CC15+CC16+CC19+CC20+CC21+CC22+CC23+CC24+CC25+CC26+CC27+CC28+CC29+CC32+CC33+CC34+CC35+CC36+CC37+CC38+CC39+CC40+CC43+CC44+CC45+CC46+CC47+CC48+CC49+CC50+CC51+CC52+CC53+CC54+CC55+CC56+CC57+CC58+CC59+CC60+CC61+CC62+CC63+CC64+CC65+CC66+CC67+CC68+CC69+CC72+CC73+CC74+CC75+CC76+CC77+CC78+CC79+CC80+CC81+CC82+CC83+CC84+CC85+CC86+CC87+CC88+CC89+CC90+CC91+CC92+CC93+CC96 | CD98: =CD8+CD9+CD12+CD13+CD14+CD15+CD16+CD19+CD20+CD21+CD22+CD23+CD24+CD25+CD26+CD27+CD28+CD29+CD32+CD33+CD34+CD35+CD36+CD37+CD38+CD39+CD40+CD43+CD44+CD45+CD46+CD47+CD48+CD49+CD50+CD51+CD52+CD53+CD54+CD55+CD56+CD57+CD58+CD59+CD60+CD61+CD62+CD63+CD64+CD65+CD66+CD67+CD68+CD69+CD72+CD73+CD74+CD75+CD76+CD77+CD78+CD79+CD80+CD81+CD82+CD83+CD84+CD85+CD86+CD87+CD88+CD89+CD90+CD91+CD92+CD93+CD96

Sheet Leyenda
B2: Leyenda de estados
C4: Not Started | D4: not_started
C5: In process | D5: in_process
C6: Approved | D6: approved
C7: Attention | D7: attention
C8: Completed | D8: completed
B11: Cómo colapsar
B13: Los botones 1 · 2 · 3 arriba a la izquierda de la hoja Job Cost Report:
B14: 1 → sólo trimestres
B15: 2 → trimestres + meses
B16: 3 → todo el detalle semanal
B17: También sirven los +/− sobre cada grupo de columnas.
B19: Este archivo es un modelo VIVO: las columnas Spend, Remaining,
B20: Forecast, los subtotales y los totales son fórmulas.
B21: Si editás el LEDGER, todo recalcula solo.
